{
  "MWEPBTN1DA": {
    "43": {
      "2": {
        "1": [
          3.02,
          11.68
        ],
        "11": [
          104.183,
          120.014
        ],
        "12": [
          120.014,
          127.974
        ],
        "13": [
          127.974,
          134.064
        ],
        "14": [
          134.064,
          152.385
        ],
        "15": [
          152.385,
          159.375
        ],
        "16": [
          159.375,
          165.895
        ],
        "17": [
          165.895,
          186.746
        ],
        "2": [
          11.68,
          19.871
        ],
        "22": [
          220.487,
          236.307
        ],
        "23": [
          236.307,
          249.878
        ],
        "24": [
          249.878,
          258.018
        ],
        "27": [
          279.059,
          286.149
        ],
        "3": [
          19.871,
          27.371
        ],
        "32": [
          335.151,
          341.011
        ],
        "33": [
          341.011,
          356.911
        ],
        "36": [
          373.042,
          387.382
        ],
        "37": [
          387.382,
          398.693
        ],
        "38": [
          398.693,
          417.623
        ],
        "4": [
          27.371,
          37.581
        ],
        "41": [
          442.594,
          454.884
        ],
        "42": [
          454.884,
          464.705
        ],
        "43": [
          464.705,
          471.245
        ],
        "44": [
          471.245,
          478.635
        ],
        "45": [
          478.635,
          485.005
        ],
        "46": [
          485.005,
          494.666
        ],
        "47": [
          494.666,
          494.666
        ],
        "5": [
          37.581,
          45.631
        ],
        "6": [
          45.631,
          59.242
        ],
        "7": [
          59.242,
          69.412
        ],
        "8": [
          69.412,
          76.072
        ]
      }
    }
  }
}