{
  "LONBSMN1DA": {
    "22": {
      "1": {
        "11": [
          90.21,
          98.32
        ],
        "12": [
          98.32,
          102.9
        ],
        "13": [
          102.9,
          121.13
        ],
        "14": [
          121.13,
          130.96
        ],
        "18": [
          180.83,
          193.91
        ],
        "19": [
          193.91,
          206.11
        ],
        "20": [
          206.11,
          224.86
        ],
        "22": [
          233.77,
          246.95
        ],
        "23": [
          246.95,
          253.34
        ],
        "24": [
          253.34,
          260.55
        ],
        "26": [
          270.53,
          281.78
        ],
        "30": [
          308.75,
          316.88
        ],
        "31": [
          316.88,
          325.48
        ],
        "32": [
          325.48,
          340.81
        ],
        "33": [
          340.81,
          347.71
        ],
        "34": [
          347.71,
          356.54
        ],
        "35": [
          356.54,
          377.89
        ],
        "38": [
          398.07,
          409.66
        ],
        "39": [
          409.66,
          417.75
        ],
        "40": [
          417.75,
          421.77
        ],
        "41": [
          421.77,
          433.03
        ],
        "5": [
          38.52,
          55.28
        ],
        "56": [
          525.49,
          531.72
        ],
        "57": [
          531.72,
          538.63
        ],
        "6": [
          55.28,
          62.49
        ],
        "62": [
          568.8,
          574.88
        ],
        "63": [
          574.88,
          583.48
        ],
        "64": [
          583.48,
          590.55
        ],
        "7": [
          62.49,
          68.72
        ],
        "8": [
          68.72,
          75.76
        ]
      }
    },
    "23": {
      "2": {
        "1": [
          2.85,
          12.54
        ],
        "10": [
          78.19,
          90.65
        ],
        "11": [
          90.65,
          99.06
        ],
        "12": [
          99.06,
          110.63
        ],
        "13": [
          110.63,
          117.96
        ],
        "14": [
          117.96,
          128.27
        ],
        "15": [
          128.27,
          141.27
        ],
        "16": [
          141.27,
          150.22
        ],
        "17": [
          150.22,
          157.43
        ],
        "4": [
          23.89,
          35.49
        ],
        "5": [
          35.49,
          41.74
        ],
        "6": [
          41.74,
          47.68
        ],
        "7": [
          47.68,
          60.02
        ],
        "8": [
          60.02,
          69.4
        ],
        "9": [
          69.4,
          78.19
        ]
      }
    },
    "24": {
      "3": {
        "15": [
          172.49,
          180.68
        ],
        "16": [
          180.68,
          198.09
        ],
        "2": [
          36.13,
          48.84
        ],
        "3": [
          48.84,
          61.04
        ],
        "4": [
          61.04,
          73.03
        ]
      }
    },
    "27": {
      "10": {
        "25": [
          255.42,
          267.08
        ],
        "26": [
          267.08,
          273.8
        ],
        "27": [
          273.8,
          288.25
        ],
        "28": [
          288.25,
          295.98
        ],
        "29": [
          295.98,
          303.81
        ],
        "30": [
          303.81,
          319.31
        ],
        "31": [
          319.31,
          326.6
        ],
        "32": [
          326.6,
          335.58
        ],
        "33": [
          335.58,
          346.24
        ],
        "34": [
          346.24,
          360.01
        ],
        "35": [
          360.01,
          373.13
        ],
        "36": [
          373.13,
          383.47
        ],
        "37": [
          383.47,
          395.84
        ]
      }
    },
    "36": {
      "9": {
        "30": [
          287.91,
          297.41
        ],
        "31": [
          297.41,
          306.36
        ],
        "33": [
          318.22,
          337.97
        ],
        "34": [
          337.97,
          348.19
        ],
        "35": [
          348.19,
          355.63
        ]
      }
    }
  }
}