{"eng":{"1":[["Again the word","H1697"],["of the LORD","H3068"],["came","H1961"],["to me","H413"],["saying","H559"]],"2":[["Son","H1121"],["of man","H120"],["confront","H3045"],["-","H853"],["Jerusalem","H3389"],["with her","H853"],["abominations","H8441"]],"3":[["and tell [her that]","H559"],["this is what","H3541"],["the Lord","H136"],["GOD","H3069"],["says","H559"],["to Jerusalem","H3389"],["Your origin","H4351"],["and your birth","H4138"],["were in the land","H776"],["of the Canaanites","H3669"],["Your father","H1"],["was an Amorite","H567"],["and your mother","H517"],["a Hittite","H2850"]],"4":[["On the day","H3117"],["of your birth","H4138"],["-","H3205"],["your cord","H8270"],["was not","H3808"],["cut","H3772"],["-","H853"],["nor","H3808"],["were you washed","H7364"],["with water","H4325"],["for cleansing","H4935"],["You were not","H3808"],["rubbed with salt","H4414"],[". . .","H4414"],["or wrapped in cloths","H2853"],[". . .","H3808"],["-","H2853"]],"5":[["No","H3808"],["one cared enough","H2347"],[". . .","H5869"],["for you","H5921"],["to do","H6213"],["even one","H259"],["of these things","H428"],["out of compassion","H2550"],["for you","H5921"],["Instead, you were thrown out","H7993"],["into","H413"],["the open","H6440"],["field","H7704"],["because you","H5315"],["were despised","H1604"],["on the day","H3117"],["of your birth","H3205"],["-","H853"]],"6":[["Then I passed","H5674"],["by","H5921"],["and saw","H7200"],["you wallowing","H947"],["in your blood","H1818"],["and as you lay there in your blood","H1818"],["I said","H559"],["to you",null],["Live","H2421"],["[There]","H1818"],["I said","H559"],["to you",null],["Live","H2421"]],"7":[["I made","H5414"],["you thrive","H7233"],["like a plant","H6780"],["of the field","H7704"],["You grew up","H7235"],["and matured","H1431"],["and became","H935"],[". . .","H5716"],["very beautiful","H5716"],["Your breasts","H7699"],["were formed","H3559"],["and your hair","H8181"],["grew","H6779"],["but you","H859"],["were naked","H5903"],["and bare","H6181"]],"8":[["Then I passed","H5674"],["by","H5921"],["and saw you","H7200"],["and you were indeed","H2009"],["old enough","H6256"],[". . .","H6256"],["for love","H1730"],["So I spread","H6566"],["My cloak","H3671"],["over you","H5921"],["and covered","H3680"],["your nakedness","H6172"],["I pledged Myself","H7650"],["to you",null],["entered","H935"],["into a covenant","H1285"],["with you","H854"],["and you became","H1961"],["Mine",null],["declares","H5002"],["the Lord","H136"],["GOD","H3069"]],"9":[["Then I bathed","H7364"],["you with water","H4325"],["rinsed off","H7857"],["your blood","H1818"],[". . .","H5921"],["and anointed","H5480"],["you with oil","H8081"]],"10":[["I clothed","H3847"],["you in embroidered cloth","H7553"],["and gave you sandals","H5274"],["of fine leather","H8476"],["I wrapped","H2280"],["you in fine linen","H8336"],["and covered","H3680"],["you with silk","H4897"]],"11":[["I adorned","H5710"],["you with jewelry","H5716"],["and I put","H5414"],["bracelets","H6781"],["on","H5921"],["your wrists","H3027"],["and a chain","H7242"],["around","H5921"],["your neck","H1627"]],"12":[["I put","H5414"],["a ring","H5141"],["in","H5921"],["your nose","H639"],["earrings","H5694"],["on","H5921"],["your ears","H241"],["and a beautiful","H8597"],["crown","H5850"],["upon your head","H7218"]],"13":[["So you were adorned","H5710"],["with gold","H2091"],["and silver","H3701"],["and your clothing [was made of]","H4403"],["fine linen","H8336"],["silk","H4897"],["and embroidered cloth","H7553"],["You ate","H398"],["fine flour","H5560"],["honey","H1706"],["and oil","H8081"],["You became very","H3966"],[". . .","H3966"],["beautiful","H3302"],["and rose to be","H6743"],["queen","H4410"]],"14":[["Your",null],["fame","H8034"],["spread","H3318"],["among the nations","H1471"],["on account of your beauty","H3308"],["for","H3588"],["it [was]","H1931"],["perfect","H3632"],["in the splendor","H1926"],["-","H834"],["I bestowed","H7760"],["on you","H5921"],["declares","H5002"],["the Lord","H136"],["GOD","H3069"]],"15":[["But because of","H5921"],["your fame","H8034"],["you trusted","H982"],["in your beauty","H3308"],["and played the harlot","H2181"],["You lavished","H8210"],["-","H853"],["your favors","H8457"],["on","H5921"],["everyone","H3605"],["who passed by","H5674"],["and your beauty was theirs for the asking","H1961"]],"16":[["You took","H3947"],["some of your garments","H899"],["and made","H6213"],["colorful","H2921"],["high places","H1116"],["for yourself",null],["and on them","H5921"],["you prostituted yourself","H2181"],["Such things should not","H3808"],["have happened","H935"],["never should","H3808"],["they have occurred","H1961"]],"17":[["You also took","H3947"],["the fine","H8597"],["jewelry","H3627"],["of gold","H2091"],["and silver","H3701"],["-","H834"],["I had given","H5414"],["you",null],["and you made","H6213"],["male","H2145"],["idols","H6754"],["with which",null],["to prostitute yourself","H2181"]],"18":[["You took","H3947"],["-","H853"],["your embroidered","H7553"],["garments","H899"],["to cover them","H3680"],["and you set","H5414"],["My oil","H8081"],["and incense","H7004"],["before them","H6440"]],"19":[["And you set","H5414"],["before them","H6440"],["as a pleasing","H5207"],["aroma","H7381"],["the food","H3899"],["-","H834"],["I had given you","H5414"],["the fine flour","H5560"],["oil","H8081"],["and honey","H1706"],["that I had fed you","H398"],["That is what happened","H1961"],["declares","H5002"],["the Lord","H136"],["GOD","H3069"]],"20":[["You even took","H3947"],["-","H853"],["the sons","H1121"],["-","H853"],["and daughters","H1323"],["-","H834"],["you bore","H3205"],["to Me",null],["and sacrificed","H2076"],["them",null],["as food to idols","H398"],["Was your prostitution","H8457"],["not enough","H4592"]],"21":[["You slaughtered","H7819"],["-","H853"],["My children","H1121"],["and delivered them up","H5414"],["through the fire","H5674"],["-","H853"],["to [idols]",null]],"22":[["And","H853"],["in all","H3605"],["your abominations","H8441"],["and acts of prostitution","H8457"],["you did not","H3808"],["remember","H2142"],["-","H853"],["the days","H3117"],["of your youth","H5271"],["when you were","H1961"],["naked","H5903"],["and bare","H6181"],["wallowing","H947"],["in your own blood","H1818"],[". . .","H1961"]],"23":[["Woe","H188"],["Woe","H188"],["to you",null],["declares","H5002"],["the Lord","H136"],["GOD","H3069"],["And","H1961"],["in addition to","H310"],["all","H3605"],["your other wickedness","H7451"]],"24":[["you built","H1129"],["yourself",null],["a mound","H1354"],["and made","H6213"],["yourself",null],["a lofty shrine","H7413"],["in every","H3605"],["public square","H7339"]],"25":[["At","H413"],["the head","H7218"],["of every","H3605"],["street","H1870"],["you built","H1129"],["your lofty shrines","H7413"],["and degraded","H8581"],["your beauty","H3308"],["With increasing","H7235"],["-","H853"],["promiscuity","H8457"],["-","H853"],["you spread","H6589"],["-","H853"],["your legs","H7272"],["to all","H3605"],["who passed by","H5674"]],"26":[["You prostituted yourself","H2181"],["with","H413"],["your lustful","H1432"],[". . .","H1320"],["neighbors","H7934"],["the Egyptians","H4714"],["and increased","H7235"],["-","H853"],["your promiscuity","H8457"],["to provoke Me to anger","H3707"]],"27":[["Therefore","H2009"],["I stretched out","H5186"],["My hand","H3027"],["against you","H5921"],["and reduced","H1639"],["your portion","H2706"],["I gave you over","H5414"],["to the desire","H5315"],["of those who hate you","H8130"],["the daughters","H1323"],["of the Philistines","H6430"],["who were ashamed","H3637"],["of your lewd","H2154"],["conduct","H1870"]],"28":[["Then you prostituted yourself","H2181"],["with","H413"],["the Assyrians","H804"],[". . .","H1121"],["because you were not yet","H1115"],["satisfied","H7646"],["Even after [that]","H2181"],["you were still","H1571"],["not","H3808"],["satisfied","H7654"]],"29":[["So you extended","H7235"],["-","H853"],["your promiscuity","H8457"],["to","H413"],["Chaldea","H3778"],["the land","H776"],["of merchants","H3667"],["but even","H1571"],["with this","H2063"],["you were not","H3808"],["satisfied","H7646"]],"30":[["How","H4100"],["weak-willed","H535"],["is your heart","H3826"],["declares","H5002"],["the Lord","H136"],["GOD","H3069"],["while you do","H6213"],["-","H853"],["all","H3605"],["these things","H428"],["the acts","H4639"],["of a shameless","H7986"],[". . .","H802"],["prostitute","H2181"]],"31":[["But when you built","H1129"],["your mounds","H1354"],["at the head","H7218"],["of every","H3605"],["street","H1870"],["and made","H6213"],["your lofty shrines","H7413"],["in every","H3605"],["public square","H7339"],["you were","H1961"],["not even like","H3808"],["a prostitute","H2181"],["because you scorned","H7046"],["payment","H868"]],"32":[["You adulterous wife","H5003"],[". . .","H802"],["You receive","H3947"],["-","H853"],["strangers","H2114"],["instead of","H8478"],["your own husband","H376"]],"33":[["Men give","H5414"],["gifts","H5078"],["to all","H3605"],["[their] prostitutes","H2181"],["but you","H859"],["gave","H5414"],["-","H853"],["gifts","H5083"],["to all","H3605"],["your lovers","H157"],["You bribed","H7809"],["them","H853"],["to come","H935"],["to you","H413"],["from everywhere","H5439"],["for your illicit favors","H8457"]],"34":[["So your",null],["prostitution","H8457"],["is","H1961"],["the opposite","H2016"],["of that","H4480"],["of other women","H802"],["No one","H3808"],["solicited","H310"],["your favors","H2181"],["and you paid","H5414"],["a fee","H868"],["instead of","H3808"],["receiving","H5414"],["one","H868"],["so you",null],["are","H1961"],["the very opposite","H2016"]],"35":[["Therefore","H3651"],["O prostitute","H2181"],["hear","H8085"],["the word","H1697"],["of the LORD","H3068"]],"36":[["This is what","H3541"],["the Lord","H136"],["GOD","H3069"],["says","H559"],["Because","H3282"],["you poured out","H8210"],["your wealth","H5178"],["and exposed","H1540"],["your nakedness","H6172"],["in your promiscuity","H8457"],["with","H5921"],["your lovers","H157"],["and with","H5921"],["all","H3605"],["your detestable","H8441"],["idols","H1544"],["and because of the blood","H1818"],["of your children","H1121"],["which","H834"],["you gave","H5414"],["to them",null]],"37":[["therefore","H3651"],["I will surely","H2005"],["gather","H6908"],["-","H853"],["all","H3605"],["the lovers","H157"],["with whom","H834"],["you found pleasure","H6149"],["all","H3605"],["those","H834"],["you loved","H157"],["-","H5921"],["and all","H3605"],["those","H834"],["you hated","H8130"],["I will gather","H6908"],["them","H853"],["against you","H5921"],["from all around","H5439"],["and expose","H1540"],["[you]","H6172"],["before them","H413"],["and they will see you","H7200"],["-","H853"],["completely","H3605"],["naked","H6172"]],"38":[["And I will sentence you","H8199"],["to the punishment","H4941"],["of women who commit adultery","H5003"],["and those who shed","H8210"],["blood","H1818"],["so I will bring upon you","H5414"],["the wrath","H2534"],["of your bloodshed","H1818"],["and jealousy","H7068"]],"39":[["Then I will deliver","H5414"],["you","H853"],["into the hands [of your lovers]","H3027"],["and they will level","H2040"],["your mounds","H1354"],["and tear down","H5422"],["your lofty shrines","H7413"],["They will strip off","H6584"],["-","H853"],["your clothes","H899"],["take","H3947"],["your fine","H8597"],["jewelry","H3627"],["and leave you","H5117"],["naked","H5903"],["and bare","H6181"]],"40":[["They will bring","H5927"],["a mob","H6951"],["against you","H5921"],["who will stone","H7275"],["you","H853"],[". . .","H68"],["and cut you to pieces","H1333"],["with their swords","H2719"]],"41":[["Then they will burn down","H8313"],[". . .","H784"],["your houses","H1004"],["and execute","H6213"],["judgment","H8201"],["against you",null],["in the sight","H5869"],["of many","H7227"],["women","H802"],["I will put an end","H7673"],["to your prostitution","H2181"],["and you will never","H3808"],[". . .","H5750"],["again","H1571"],["pay","H5414"],["your lovers","H868"]],"42":[["So I will lay to rest","H5117"],["My wrath","H2534"],["against you",null],["and My jealousy","H7068"],["will turn away","H5493"],["from you","H4480"],["Then I will be calm","H8252"],["and no","H3808"],["longer","H5750"],["angry","H3707"]],"43":[["Because","H3282"],["-","H834"],["you did not","H3808"],["remember","H2142"],["-","H853"],["the days","H3117"],["of your youth","H5271"],["but enraged","H7264"],["Me",null],["with all","H3605"],["these","H428"],["things","H589"],[". . .","H1887"],["I will surely","H1571"],["bring your deeds","H1870"],["down","H5414"],["upon your own head","H7218"],["declares","H5002"],["the Lord","H136"],["GOD","H3069"],["Have you not","H3808"],["committed","H6213"],["-","H853"],["this lewdness","H2154"],["on top","H5921"],["of all","H3605"],["your [other] abominations","H8441"]],"44":[["Behold","H2009"],["all","H3605"],["who speak in proverbs","H4911"],["will quote this proverb","H4911"],[". . .","H559"],["about you","H5921"],["Like mother","H517"],["like daughter","H1323"]],"45":[["You","H859"],["are the daughter","H1323"],["of your mother","H517"],["who despised","H1602"],["her husband","H376"],["and children","H1121"],["You","H859"],["are the sister","H269"],["of your sisters","H269"],["who","H834"],["despised","H1602"],["their husbands","H582"],["and children","H1121"],["Your mother","H517"],["was a Hittite","H2850"],["and your father","H1"],["an Amorite","H567"]],"46":[["Your older","H1419"],["sister","H269"],["was Samaria","H8111"],["who","H1931"],["lived","H3427"],["with her daughters","H1323"],["to","H5921"],["your north","H8040"],["and your younger","H6996"],["sister","H269"],["was Sodom","H5467"],["who lived","H3427"],["with her daughters","H1323"],["to","H4480"],["your south","H3225"]],"47":[["And you not only","H3808"],["walked","H1980"],["in their",null],["-","H3605"],["-","H1870"],["ways","H1870"],["and practiced","H6213"],["their abominations","H8441"],["but soon you were","H4592"],[". . .","H6985"],["more depraved than they were","H7843"]],"48":[["As surely as I","H589"],["live","H2416"],["declares","H5002"],["the Lord","H136"],["GOD","H3069"],["your sister","H269"],[". . .","H1931"],["Sodom","H5467"],["and her daughters","H1323"],["never","H518"],["did","H6213"],["as","H834"],["you","H859"],["and your daughters","H1323"],["have done","H6213"]],"49":[["Now","H2009"],["this","H2088"],["was","H1961"],["the iniquity","H5771"],["of your sister","H269"],["Sodom","H5467"],["She",null],["and her daughters","H1323"],[". . .","H3027"],["were","H1961"],["arrogant","H1347"],["overfed","H7653"],[". . .","H3899"],["and complacent","H8252"],[". . .","H7962"],["they did not","H3808"],["help","H2388"],["the poor","H6041"],["and needy","H34"]],"50":[["Thus they were haughty","H1361"],["and committed","H6213"],["abominations","H8441"],["before Me","H6440"],["Therefore I removed","H5493"],["them","H853"],["as","H834"],["you have seen","H7200"]],"51":[["Furthermore, Samaria","H8111"],["did not","H3808"],["commit","H2398"],["half","H2677"],["the sins you did","H2403"],["You have multiplied","H7235"],["-","H853"],["your abominations","H8441"],["beyond theirs",null],["and all","H3605"],["the abominations","H8441"],["-","H834"],["you have committed","H6213"],["have made your sisters","H269"],["appear righteous","H6663"],["-","H853"]],"52":[["So now","H1571"],["you","H859"],["must bear","H5375"],["your disgrace","H3639"],["since","H834"],["you have brought justification","H6419"],["for your sisters","H269"],["For they appear more righteous","H6663"],["than you","H4480"],["because your sins","H2403"],["-","H834"],["were more vile","H8581"],["than theirs",null],["So you","H859"],["too","H1571"],["must bear","H5375"],["your shame","H954"],["and disgrace","H3639"],["since you have made your sisters","H269"],["appear righteous","H6663"]],"53":[["But I will restore","H7725"],["-","H853"],["-","H853"],["-","H7622"],["Sodom","H5467"],["and her daughters","H1323"],["from captivity","H7622"],["-","H853"],["as well as","H7622"],["Samaria","H8111"],["and her daughters","H1323"],["And I will restore you","H7622"],[". . .","H7622"],["along with them","H8432"]],"54":[["So","H4616"],["you will bear","H5375"],["your disgrace","H3639"],["and be ashamed","H3637"],["of all","H3605"],["-","H834"],["you did","H6213"],["to comfort them","H5162"],["-","H853"]],"55":[["And your sisters","H269"],["Sodom","H5467"],["with her daughters","H1323"],["and Samaria","H8111"],["with her daughters","H1323"],["will return","H7725"],["to their former state","H6927"],["You","H859"],["and your daughters","H1323"],[". . .","H7725"],[". . .","H6927"],["will also return","H7725"],["to your former state","H6927"]],"56":[["Did you not","H3808"],["treat","H1961"],[". . .","H6310"],["your sister","H269"],["Sodom","H5467"],["as an object of scorn","H8052"],["in the day","H3117"],["of your pride","H1347"]],"57":[["before","H2962"],["your wickedness","H7451"],["was uncovered","H1540"],["Even so","H3644"],["you are now","H6256"],["scorned","H2781"],["by the daughters","H1323"],["of Edom","H758"],["and all","H3605"],["those around her","H5439"],["and by the daughters","H1323"],["of the Philistines","H6430"],["all those around you","H5439"],["who despise","H7590"],["you","H853"]],"58":[["-","H853"],["You","H859"],["will bear the consequences","H5375"],["of your lewdness","H2154"],["and","H853"],["your abominations","H8441"],["declares","H5002"],["the LORD","H3068"]],"59":[["For","H3588"],["this is what","H3541"],["the Lord","H136"],["GOD","H3069"],["says","H559"],["I will deal","H6213"],["with you","H854"],["according to","H834"],["your deeds","H6213"],["since","H834"],["you have despised","H959"],["the oath","H423"],["by breaking","H6565"],["the covenant","H1285"]],"60":[["But I","H589"],["-","H853"],["will remember","H2142"],["the covenant","H1285"],[". . .","H1285"],["I made with you","H854"],["in the days","H3117"],["of your youth","H5271"],["and I will establish","H6965"],["an everlasting covenant","H5769"],["with you",null]],"61":[["Then you will remember","H2142"],["-","H853"],["your ways","H1870"],["and be ashamed","H3637"],["when you receive","H3947"],["-","H853"],["your older","H1419"],["and","H413"],["younger","H6996"],[". . .","H4480"],["sisters","H269"],["I will give","H5414"],["them","H853"],["to you",null],["as daughters","H1323"],["but not because of","H3808"],["My covenant with you","H1285"]],"62":[["So I","H589"],["-","H853"],["will establish","H6965"],["My covenant","H1285"],["with you","H854"],["and you will know","H3045"],["that","H3588"],["I","H589"],["am the LORD","H3068"]],"63":[["so that","H4616"],["when I make atonement","H3722"],["for","H3605"],["all","H834"],["you have done","H6213"],["you will remember","H2142"],["and be ashamed","H954"],["and never","H3808"],[". . .","H1961"],["again","H5750"],["open","H6610"],["your mouth","H6310"],["because of","H6440"],["your disgrace","H3639"],["declares","H5002"],["the Lord","H136"],["GOD","H3069"]]},"heb":{"1":[["וַיְהִ֥י","H1961"],["דְבַר־","H1697"],["יְהוָ֖ה","H3068"],["אֵלַ֥י","H413"],["לֵאמֹֽר׃","H559"]],"2":[["בֶּן־","H1121"],["אָדָ֕ם","H120"],["הוֹדַ֥ע","H3045"],["אֶת־","H853"],["יְרוּשָׁלִַ֖ם","H3389"],["אֶת־","H853"],["תּוֹעֲבֹתֶֽיהָ׃","H8441"]],"3":[["וְאָמַרְתָּ֞","H559"],["כֹּה־","H3541"],["אָמַ֨ר","H559"],["אֲדֹנָ֤י","H136"],["יְהוִה֙","H3069"],["לִיר֣וּשָׁלִַ֔ם","H3389"],["מְכֹרֹתַ֙יִךְ֙","H4351"],["וּמֹ֣לְדֹתַ֔יִךְ","H4138"],["מֵאֶ֖רֶץ","H776"],["הַֽכְּנַעֲנִ֑י","H3669"],["אָבִ֥יךְ","H1"],["הָאֱמֹרִ֖י","H567"],["וְאִמֵּ֥ךְ","H517"],["חִתִּֽית׃","H2850"]],"4":[["וּמוֹלְדוֹתַ֗יִךְ","H4138"],["בְּי֨וֹם","H3117"],["הוּלֶּ֤דֶת","H3205"],["אֹתָךְ֙","H853"],["לֹֽא־","H3808"],["כָרַּ֣ת","H3772"],["שָׁרֵּ֔ךְ","H8270"],["וּבְמַ֥יִם","H4325"],["לֹֽא־","H3808"],["רֻחַ֖צְתְּ","H7364"],["לְמִשְׁעִ֑י","H4935"],["וְהָמְלֵ֙חַ֙","H4414"],["לֹ֣א","H3808"],["הֻמְלַ֔חַתְּ","H4414"],["וְהָחְתֵּ֖ל","H2853"],["לֹ֥א","H3808"],["חֻתָּֽלְתְּ׃","H2853"]],"5":[["לֹא־","H3808"],["חָ֨סָה","H2347"],["עָלַ֜יִךְ","H5921"],["עַ֗יִן","H5869"],["לַעֲשׂ֥וֹת","H6213"],["לָ֛ךְ",null],["אַחַ֥ת","H259"],["מֵאֵ֖לֶּה","H428"],["לְחֻמְלָ֣ה","H2550"],["עָלָ֑יִךְ","H5921"],["וַֽתֻּשְׁלְכִ֞י","H7993"],["אֶל־","H413"],["פְּנֵ֤י","H6440"],["הַשָּׂדֶה֙","H7704"],["בְּגֹ֣עַל","H1604"],["נַפְשֵׁ֔ךְ","H5315"],["בְּי֖וֹם","H3117"],["הֻלֶּ֥דֶת","H3205"],["אֹתָֽךְ׃","H853"]],"6":[["וָאֶעֱבֹ֤ר","H5674"],["עָלַ֙יִךְ֙","H5921"],["וָֽאֶרְאֵ֔ךְ","H7200"],["מִתְבּוֹסֶ֖סֶת","H947"],["בְּדָמָ֑יִךְ","H1818"],["וָאֹ֤מַר","H559"],["לָךְ֙",null],["בְּדָמַ֣יִךְ","H1818"],["חֲיִ֔י","H2421"],["וָאֹ֥מַר","H559"],["לָ֖ךְ",null],["בְּדָמַ֥יִךְ","H1818"],["חֲיִֽי׃","H2421"]],"7":[["רְבָבָ֗ה","H7233"],["כְּצֶ֤מַח","H6780"],["הַשָּׂדֶה֙","H7704"],["נְתַתִּ֔יךְ","H5414"],["וַתִּרְבִּי֙","H7235"],["וַֽתִּגְדְּלִ֔י","H1431"],["וַתָּבֹ֖אִי","H935"],["בַּעֲדִ֣י","H5716"],["עֲדָיִ֑ים","H5716"],["שָׁדַ֤יִם","H7699"],["נָכֹ֙נוּ֙","H3559"],["וּשְׂעָרֵ֣ךְ","H8181"],["צִמֵּ֔חַ","H6779"],["וְאַ֖תְּ","H859"],["עֵרֹ֥ם","H5903"],["וְעֶרְיָֽה׃","H6181"]],"8":[["וָאֶעֱבֹ֨ר","H5674"],["עָלַ֜יִךְ","H5921"],["וָאֶרְאֵ֗ךְ","H7200"],["וְהִנֵּ֤ה","H2009"],["עִתֵּךְ֙","H6256"],["עֵ֣ת","H6256"],["דֹּדִ֔ים","H1730"],["וָאֶפְרֹ֤שׂ","H6566"],["כְּנָפִי֙","H3671"],["עָלַ֔יִךְ","H5921"],["וָאֲכַסֶּ֖ה","H3680"],["עֶרְוָתֵ֑ךְ","H6172"],["וָאֶשָּׁ֣בַֽע","H7650"],["לָ֠ךְ",null],["וָאָב֨וֹא","H935"],["בִבְרִ֜ית","H1285"],["אֹתָ֗ךְ","H854"],["נְאֻ֛ם","H5002"],["אֲדֹנָ֥י","H136"],["יְהוִ֖ה","H3069"],["וַתִּ֥הְיִי","H1961"],["לִֽי׃",null]],"9":[["וָאֶרְחָצֵ֣ךְ","H7364"],["בַּמַּ֔יִם","H4325"],["וָאֶשְׁטֹ֥ף","H7857"],["דָּמַ֖יִךְ","H1818"],["מֵֽעָלָ֑יִךְ","H5921"],["וָאֲסֻכֵ֖ךְ","H5480"],["בַּשָּֽׁמֶן׃","H8081"]],"10":[["וָאַלְבִּישֵׁ֣ךְ","H3847"],["רִקְמָ֔ה","H7553"],["וָאֶנְעֲלֵ֖ךְ","H5274"],["תָּ֑חַשׁ","H8476"],["וָאֶחְבְּשֵׁ֣ךְ","H2280"],["בַּשֵּׁ֔שׁ","H8336"],["וַאֲכַסֵּ֖ךְ","H3680"],["מֶֽשִׁי׃","H4897"]],"11":[["וָאֶעְדֵּ֖ךְ","H5710"],["עֶ֑דִי","H5716"],["וָאֶתְּנָ֤ה","H5414"],["צְמִידִים֙","H6781"],["עַל־","H5921"],["יָדַ֔יִךְ","H3027"],["וְרָבִ֖יד","H7242"],["עַל־","H5921"],["גְּרוֹנֵֽךְ׃","H1627"]],"12":[["וָאֶתֵּ֥ן","H5414"],["נֶ֙זֶם֙","H5141"],["עַל־","H5921"],["אַפֵּ֔ךְ","H639"],["וַעֲגִילִ֖ים","H5694"],["עַל־","H5921"],["אָזְנָ֑יִךְ","H241"],["וַעֲטֶ֥רֶת","H5850"],["תִּפְאֶ֖רֶת","H8597"],["בְּרֹאשֵֽׁךְ׃","H7218"]],"13":[["וַתַּעְדִּ֞י","H5710"],["זָהָ֣ב","H2091"],["וָכֶ֗סֶף","H3701"],["וּמַלְבּוּשֵׁךְ֙","H4403"],["שֵׁשִׁי","H8336"],["וָמֶ֙שִׁי֙","H4897"],["וְרִקְמָ֔ה","H7553"],["סֹ֧לֶת","H5560"],["וּדְבַ֛שׁ","H1706"],["וָשֶׁ֖מֶן","H8081"],["אָכָלְתִּי","H398"],["וַתִּ֙יפִי֙","H3302"],["בִּמְאֹ֣ד","H3966"],["מְאֹ֔ד","H3966"],["וַֽתִּצְלְחִ֖י","H6743"],["לִמְלוּכָֽה׃","H4410"]],"14":[["וַיֵּ֨צֵא","H3318"],["לָ֥ךְ",null],["שֵׁ֛ם","H8034"],["בַּגּוֹיִ֖ם","H1471"],["בְּיָפְיֵ֑ךְ","H3308"],["כִּ֣י׀","H3588"],["כָּלִ֣יל","H3632"],["ה֗וּא","H1931"],["בַּֽהֲדָרִי֙","H1926"],["אֲשֶׁר־","H834"],["שַׂ֣מְתִּי","H7760"],["עָלַ֔יִךְ","H5921"],["נְאֻ֖ם","H5002"],["אֲדֹנָ֥י","H136"],["יְהוִֽה׃","H3069"]],"15":[["וַתִּבְטְחִ֣י","H982"],["בְיָפְיֵ֔ךְ","H3308"],["וַתִּזְנִ֖י","H2181"],["עַל־","H5921"],["שְׁמֵ֑ךְ","H8034"],["וַתִּשְׁפְּכִ֧י","H8210"],["אֶת־","H853"],["תַּזְנוּתַ֛יִךְ","H8457"],["עַל־","H5921"],["כָּל־","H3605"],["עוֹבֵ֖ר","H5674"],["לוֹ־",null],["יֶֽהִי׃","H1961"]],"16":[["וַתִּקְחִ֣י","H3947"],["מִבְּגָדַ֗יִךְ","H899"],["וַתַּֽעֲשִׂי־","H6213"],["לָךְ֙",null],["בָּמ֣וֹת","H1116"],["טְלֻא֔וֹת","H2921"],["וַתִּזְנִ֖י","H2181"],["עֲלֵיהֶ֑ם","H5921"],["לֹ֥א","H3808"],["בָא֖וֹת","H935"],["וְלֹ֥א","H3808"],["יִהְיֶֽה׃","H1961"]],"17":[["וַתִּקְחִ֞י","H3947"],["כְּלֵ֣י","H3627"],["תִפְאַרְתֵּ֗ךְ","H8597"],["מִזְּהָבִ֤י","H2091"],["וּמִכַּסְפִּי֙","H3701"],["אֲשֶׁ֣ר","H834"],["נָתַ֣תִּי","H5414"],["לָ֔ךְ",null],["וַתַּעֲשִׂי־","H6213"],["לָ֖ךְ",null],["צַלְמֵ֣י","H6754"],["זָכָ֑ר","H2145"],["וַתִּזְנִי־","H2181"],["בָֽם׃",null]],"18":[["וַתִּקְחִ֛י","H3947"],["אֶת־","H853"],["בִּגְדֵ֥י","H899"],["רִקְמָתֵ֖ךְ","H7553"],["וַתְּכַסִּ֑ים","H3680"],["וְשַׁמְנִי֙","H8081"],["וּקְטָרְתִּ֔י","H7004"],["נָתַתִּי","H5414"],["לִפְנֵיהֶֽם׃","H6440"]],"19":[["וְלַחְמִי֩","H3899"],["אֲשֶׁר־","H834"],["נָתַ֨תִּי","H5414"],["לָ֜ךְ",null],["סֹ֣לֶת","H5560"],["וָשֶׁ֤מֶן","H8081"],["וּדְבַשׁ֙","H1706"],["הֶֽאֱכַלְתִּ֔יךְ","H398"],["וּנְתַתִּ֧יהוּ","H5414"],["לִפְנֵיהֶ֛ם","H6440"],["לְרֵ֥יחַ","H7381"],["נִיחֹ֖חַ","H5207"],["וַיֶּ֑הִי","H1961"],["נְאֻ֖ם","H5002"],["אֲדֹנָ֥י","H136"],["יְהוִֽה׃","H3069"]],"20":[["וַתִּקְחִ֞י","H3947"],["אֶת־","H853"],["בָּנַ֤יִךְ","H1121"],["וְאֶת־","H853"],["בְּנוֹתַ֙יִךְ֙","H1323"],["אֲשֶׁ֣ר","H834"],["יָלַ֣דְתְּ","H3205"],["לִ֔י",null],["וַתִּזְבָּחִ֥ים","H2076"],["לָהֶ֖ם",null],["לֶאֱכ֑וֹל","H398"],["הַמְעַ֖ט","H4592"],["מִתַּזְנֻתֵךְ׃","H8457"]],"21":[["וַֽתִּשְׁחֲטִ֖י","H7819"],["אֶת־","H853"],["בָּנָ֑י","H1121"],["וַֽתִּתְּנִ֔ים","H5414"],["בְּהַעֲבִ֥יר","H5674"],["אוֹתָ֖ם","H853"],["לָהֶֽם׃",null]],"22":[["וְאֵ֤ת","H853"],["כָּל־","H3605"],["תּוֹעֲבֹתַ֙יִךְ֙","H8441"],["וְתַזְנֻתַ֔יִךְ","H8457"],["לֹ֥א","H3808"],["זָכַרְתִּי","H2142"],["אֶת־","H853"],["יְמֵ֣י","H3117"],["נְעוּרָ֑יִךְ","H5271"],["בִּֽהְיוֹתֵךְ֙","H1961"],["עֵרֹ֣ם","H5903"],["וְעֶרְיָ֔ה","H6181"],["מִתְבּוֹסֶ֥סֶת","H947"],["בְּדָמֵ֖ךְ","H1818"],["הָיִֽית׃","H1961"]],"23":[["וַיְהִ֕י","H1961"],["אַחֲרֵ֖י","H310"],["כָּל־","H3605"],["רָעָתֵ֑ךְ","H7451"],["א֣וֹי","H188"],["א֣וֹי","H188"],["לָ֔ךְ",null],["נְאֻ֖ם","H5002"],["אֲדֹנָ֥י","H136"],["יְהוִֽה׃","H3069"]],"24":[["וַתִּבְנִי־","H1129"],["לָ֖ךְ",null],["גֶּ֑ב","H1354"],["וַתַּעֲשִׂי־","H6213"],["לָ֥ךְ",null],["רָמָ֖ה","H7413"],["בְּכָל־","H3605"],["רְחֽוֹב׃","H7339"]],"25":[["אֶל־","H413"],["כָּל־","H3605"],["רֹ֣אשׁ","H7218"],["דֶּ֗רֶךְ","H1870"],["בָּנִית֙","H1129"],["רָֽמָתֵ֔ךְ","H7413"],["וַתְּתַֽעֲבִי֙","H8581"],["אֶת־","H853"],["יָפְיֵ֔ךְ","H3308"],["וַתְּפַשְּׂקִ֥י","H6589"],["אֶת־","H853"],["רַגְלַ֖יִךְ","H7272"],["לְכָל־","H3605"],["עוֹבֵ֑ר","H5674"],["וַתַּרְבִּ֖י","H7235"],["אֶת־","H853"],["תַּזְנֻתֵךְ׃","H8457"]],"26":[["וַתִּזְנִ֧י","H2181"],["אֶל־","H413"],["בְּנֵֽי־","H1121"],["מִצְרַ֛יִם","H4714"],["שְׁכֵנַ֖יִךְ","H7934"],["גִּדְלֵ֣י","H1432"],["בָשָׂ֑ר","H1320"],["וַתַּרְבִּ֥י","H7235"],["אֶת־","H853"],["תַּזְנֻתֵ֖ךְ","H8457"],["לְהַכְעִיסֵֽנִי׃","H3707"]],"27":[["וְהִנֵּ֨ה","H2009"],["נָטִ֤יתִי","H5186"],["יָדִי֙","H3027"],["עָלַ֔יִךְ","H5921"],["וָאֶגְרַ֖ע","H1639"],["חֻקֵּ֑ךְ","H2706"],["וָאֶתְּנֵ֞ךְ","H5414"],["בְּנֶ֤פֶשׁ","H5315"],["שֹׂנְאוֹתַ֙יִךְ֙","H8130"],["בְּנ֣וֹת","H1323"],["פְּלִשְׁתִּ֔ים","H6430"],["הַנִּכְלָמ֖וֹת","H3637"],["מִדַּרְכֵּ֥ךְ","H1870"],["זִמָּֽה׃","H2154"]],"28":[["וַתִּזְנִי֙","H2181"],["אֶל־","H413"],["בְּנֵ֣י","H1121"],["אַשּׁ֔וּר","H804"],["מִבִּלְתִּ֖י","H1115"],["שָׂבְעָתֵ֑ךְ","H7654"],["וַתִּזְנִ֕ים","H2181"],["וְגַ֖ם","H1571"],["לֹ֥א","H3808"],["שָׂבָֽעַתְּ׃","H7646"]],"29":[["וַתַּרְבִּ֧י","H7235"],["אֶת־","H853"],["תַּזְנוּתֵ֛ךְ","H8457"],["אֶל־","H413"],["אֶ֥רֶץ","H776"],["כְּנַ֖עַן","H3667"],["כַּשְׂדִּ֑ימָה","H3778"],["וְגַם־","H1571"],["בְּזֹ֖את","H2063"],["לֹ֥א","H3808"],["שָׂבָֽעַתְּ׃","H7646"]],"30":[["מָ֤ה","H4100"],["אֲמֻלָה֙","H535"],["לִבָּתֵ֔ךְ","H3826"],["נְאֻ֖ם","H5002"],["אֲדֹנָ֣י","H136"],["יְהוִ֑ה","H3069"],["בַּעֲשׂוֹתֵךְ֙","H6213"],["אֶת־","H853"],["כָּל־","H3605"],["אֵ֔לֶּה","H428"],["מַעֲשֵׂ֥ה","H4639"],["אִשָּֽׁה־","H802"],["זוֹנָ֖ה","H2181"],["שַׁלָּֽטֶת׃","H7986"]],"31":[["בִּבְנוֹתַ֤יִךְ","H1129"],["גַּבֵּךְ֙","H1354"],["בְּרֹ֣אשׁ","H7218"],["כָּל־","H3605"],["דֶּ֔רֶךְ","H1870"],["וְרָמָתֵ֥ךְ","H7413"],["עָשִׂיתִי","H6213"],["בְּכָל־","H3605"],["רְח֑וֹב","H7339"],["וְלֹא־","H3808"],["הָיִיתי","H1961"],["כַּזּוֹנָ֖ה","H2181"],["לְקַלֵּ֥ס","H7046"],["אֶתְנָֽן׃","H868"]],"32":[["הָאִשָּׁ֖ה","H802"],["הַמְּנָאָ֑פֶת","H5003"],["תַּ֣חַת","H8478"],["אִישָׁ֔הּ","H376"],["תִּקַּ֖ח","H3947"],["אֶת־","H853"],["זָרִֽים׃","H2114"]],"33":[["לְכָל־","H3605"],["זֹנ֖וֹת","H2181"],["יִתְּנוּ־","H5414"],["נֵ֑דֶה","H5078"],["וְאַ֨תְּ","H859"],["נָתַ֤תְּ","H5414"],["אֶת־","H853"],["נְדָנַ֙יִךְ֙","H5083"],["לְכָל־","H3605"],["מְאַֽהֲבַ֔יִךְ","H157"],["וַתִּשְׁחֳדִ֣י","H7809"],["אוֹתָ֗ם","H853"],["לָב֥וֹא","H935"],["אֵלַ֛יִךְ","H413"],["מִסָּבִ֖יב","H5439"],["בְּתַזְנוּתָֽיִךְ׃","H8457"]],"34":[["וַיְהִי־","H1961"],["בָ֨ךְ",null],["הֵ֤פֶךְ","H2016"],["מִן־","H4480"],["הַנָּשִׁים֙","H802"],["בְּתַזְנוּתַ֔יִךְ","H8457"],["וְאַחֲרַ֖יִךְ","H310"],["לֹ֣א","H3808"],["זוּנָּ֑ה","H2181"],["וּבְתִתֵּ֣ךְ","H5414"],["אֶתְנָ֗ן","H868"],["וְאֶתְנַ֛ן","H868"],["לֹ֥א","H3808"],["נִתַּן־","H5414"],["לָ֖ךְ",null],["וַתְּהִ֥י","H1961"],["לְהֶֽפֶךְ׃","H2016"]],"35":[["לָכֵ֣ן","H3651"],["זוֹנָ֔ה","H2181"],["שִׁמְעִ֖י","H8085"],["דְּבַר־","H1697"],["יְהוָֽה׃פ","H3068"]],"36":[["כֹּֽה־","H3541"],["אָמַ֞ר","H559"],["אֲדֹנָ֣י","H136"],["יְהֹוִ֗ה","H3069"],["יַ֣עַן","H3282"],["הִשָּׁפֵ֤ךְ","H8210"],["נְחֻשְׁתֵּךְ֙","H5178"],["וַתִּגָּלֶ֣ה","H1540"],["עֶרְוָתֵ֔ךְ","H6172"],["בְּתַזְנוּתַ֖יִךְ","H8457"],["עַל־","H5921"],["מְאַהֲבָ֑יִךְ","H157"],["וְעַל֙","H5921"],["כָּל־","H3605"],["גִּלּוּלֵ֣י","H1544"],["תוֹעֲבוֹתַ֔יִךְ","H8441"],["וְכִדְמֵ֣י","H1818"],["בָנַ֔יִךְ","H1121"],["אֲשֶׁ֥ר","H834"],["נָתַ֖תְּ","H5414"],["לָהֶֽם׃",null]],"37":[["לָ֠כֵן","H3651"],["הִנְנִ֨י","H2005"],["מְקַבֵּ֤ץ","H6908"],["אֶת־","H853"],["כָּל־","H3605"],["מְאַהֲבַ֙יִךְ֙","H157"],["אֲשֶׁ֣ר","H834"],["עָרַ֣בְתְּ","H6149"],["עֲלֵיהֶ֔ם","H5921"],["וְאֵת֙","H853"],["כָּל־","H3605"],["אֲשֶׁ֣ר","H834"],["אָהַ֔בְתְּ","H157"],["עַ֖ל","H5921"],["כָּל־","H3605"],["אֲשֶׁ֣ר","H834"],["שָׂנֵ֑את","H8130"],["וְקִבַּצְתִּי֩","H6908"],["אֹתָ֨ם","H853"],["עָלַ֜יִךְ","H5921"],["מִסָּבִ֗יב","H5439"],["וְגִלֵּיתִ֤י","H1540"],["עֶרְוָתֵךְ֙","H6172"],["אֲלֵהֶ֔ם","H413"],["וְרָא֖וּ","H7200"],["אֶת־","H853"],["כָּל־","H3605"],["עֶרְוָתֵֽךְ׃","H6172"]],"38":[["וּשְׁפַטְתִּיךְ֙","H8199"],["מִשְׁפְּטֵ֣י","H4941"],["נֹאֲפ֔וֹת","H5003"],["וְשֹׁפְכֹ֖ת","H8210"],["דָּ֑ם","H1818"],["וּנְתַתִּ֕יךְ","H5414"],["דַּ֥ם","H1818"],["חֵמָ֖ה","H2534"],["וְקִנְאָֽה׃","H7068"]],"39":[["וְנָתַתִּ֨י","H5414"],["אוֹתָ֜ךְ","H853"],["בְּיָדָ֗ם","H3027"],["וְהָרְס֤וּ","H2040"],["גַבֵּךְ֙","H1354"],["וְנִתְּצ֣וּ","H5422"],["רָמֹתַ֔יִךְ","H7413"],["וְהִפְשִׁ֤יטוּ","H6584"],["אוֹתָךְ֙","H853"],["בְּגָדַ֔יִךְ","H899"],["וְלָקְח֖וּ","H3947"],["כְּלֵ֣י","H3627"],["תִפְאַרְתֵּ֑ךְ","H8597"],["וְהִנִּיח֖וּךְ","H5117"],["עֵירֹ֥ם","H5903"],["וְעֶרְיָֽה׃","H6181"]],"40":[["וְהֶעֱל֤וּ","H5927"],["עָלַ֙יִךְ֙","H5921"],["קָהָ֔ל","H6951"],["וְרָגְמ֥וּ","H7275"],["אוֹתָ֖ךְ","H853"],["בָּאָ֑בֶן","H68"],["וּבִתְּק֖וּךְ","H1333"],["בְּחַרְבוֹתָֽם׃","H2719"]],"41":[["וְשָׂרְפ֤וּ","H8313"],["בָתַּ֙יִךְ֙","H1004"],["בָּאֵ֔שׁ","H784"],["וְעָשׂוּ־","H6213"],["בָ֣ךְ",null],["שְׁפָטִ֔ים","H8201"],["לְעֵינֵ֖י","H5869"],["נָשִׁ֣ים","H802"],["רַבּ֑וֹת","H7227"],["וְהִשְׁבַּתִּיךְ֙","H7673"],["מִזּוֹנָ֔ה","H2181"],["וְגַם־","H1571"],["אֶתְנַ֖ן","H868"],["לֹ֥א","H3808"],["תִתְּנִי־","H5414"],["עֽוֹד׃","H5750"]],"42":[["וַהֲנִחֹתִ֤י","H5117"],["חֲמָתִי֙","H2534"],["בָּ֔ךְ",null],["וְסָ֥רָה","H5493"],["קִנְאָתִ֖י","H7068"],["מִמֵּ֑ךְ","H4480"],["וְשָׁ֣קַטְתִּ֔י","H8252"],["וְלֹ֥א","H3808"],["אֶכְעַ֖ס","H3707"],["עֽוֹד׃","H5750"]],"43":[["יַ֗עַן","H3282"],["אֲשֶׁ֤ר","H834"],["לֹֽא־","H3808"],["זָכַרְתִּי","H2142"],["אֶת־","H853"],["יְמֵ֣י","H3117"],["נְעוּרַ֔יִךְ","H5271"],["וַתִּרְגְּזִי־","H7264"],["לִ֖י",null],["בְּכָל־","H3605"],["אֵ֑לֶּה","H428"],["וְגַם־","H1571"],["אֲנִ֨י","H589"],["הֵ֜א","H1887"],["דַּרְכֵּ֣ךְ׀","H1870"],["בְּרֹ֣אשׁ","H7218"],["נָתַ֗תִּי","H5414"],["נְאֻם֙","H5002"],["אֲדֹנָ֣י","H136"],["יְהוִ֔ה","H3069"],["וְלֹ֤א","H3808"],["עָשִׂיתִי","H6213"],["אֶת־","H853"],["הַזִּמָּ֔ה","H2154"],["עַ֖ל","H5921"],["כָּל־","H3605"],["תּוֹעֲבֹתָֽיִךְ׃","H8441"]],"44":[["הִנֵּה֙","H2009"],["כָּל־","H3605"],["הַמֹּשֵׁ֔ל","H4911"],["עָלַ֥יִךְ","H5921"],["יִמְשֹׁ֖ל","H4911"],["לֵאמֹ֑ר","H559"],["כְּאִמָּ֖ה","H517"],["בִּתָּֽהּ׃","H1323"]],"45":[["בַּת־","H1323"],["אִמֵּ֣ךְ","H517"],["אַ֔תְּ","H859"],["גֹּעֶ֥לֶת","H1602"],["אִישָׁ֖הּ","H376"],["וּבָנֶ֑יהָ","H1121"],["וַאֲח֨וֹת","H269"],["אֲחוֹתֵ֜ךְ","H269"],["אַ֗תְּ","H859"],["אֲשֶׁ֤ר","H834"],["גָּֽעֲ֙לוּ֙","H1602"],["אַנְשֵׁיהֶ֣ן","H582"],["וּבְנֵיהֶ֔ן","H1121"],["אִמְּכֶ֣ן","H517"],["חִתִּ֔ית","H2850"],["וַאֲבִיכֶ֖ן","H1"],["אֱמֹרִֽי׃","H567"]],"46":[["וַאֲחוֹתֵ֨ךְ","H269"],["הַגְּדוֹלָ֤ה","H1419"],["שֹֽׁמְרוֹן֙","H8111"],["הִ֣יא","H1931"],["וּבְנוֹתֶ֔יהָ","H1323"],["הַיּוֹשֶׁ֖בֶת","H3427"],["עַל־","H5921"],["שְׂמֹאולֵ֑ךְ","H8040"],["וַאֲחוֹתֵ֞ךְ","H269"],["הַקְּטַנָּ֣ה","H6996"],["מִמֵּ֗ךְ","H4480"],["הַיּוֹשֶׁ֙בֶת֙","H3427"],["מִֽימִינֵ֔ךְ","H3225"],["סְדֹ֖ם","H5467"],["וּבְנוֹתֶֽיהָ׃","H1323"]],"47":[["וְלֹ֤א","H3808"],["בְדַרְכֵיהֶן֙","H1870"],["הָלַ֔כְתְּ","H1980"],["וּבְתוֹעֲבֽוֹתֵיהֶ֖ן","H8441"],["עָשִׂיתִי","H6213"],["כִּמְעַ֣ט","H4592"],["קָ֔ט","H6985"],["וַתַּשְׁחִ֥תִי","H7843"],["מֵהֵ֖ן",null],["בְּכָל־","H3605"],["דְּרָכָֽיִךְ׃","H1870"]],"48":[["חַי־","H2416"],["אָ֗נִי","H589"],["נְאֻם֙","H5002"],["אֲדֹנָ֣י","H136"],["יְהוִ֔ה","H3069"],["אִם־","H518"],["עָֽשְׂתָה֙","H6213"],["סְדֹ֣ם","H5467"],["אֲחוֹתֵ֔ךְ","H269"],["הִ֖יא","H1931"],["וּבְנוֹתֶ֑יהָ","H1323"],["כַּאֲשֶׁ֣ר","H834"],["עָשִׂ֔ית","H6213"],["אַ֖תְּ","H859"],["וּבְנוֹתָֽיִךְ׃","H1323"]],"49":[["הִנֵּה־","H2009"],["זֶ֣ה","H2088"],["הָיָ֔ה","H1961"],["עֲוֺ֖ן","H5771"],["סְדֹ֣ם","H5467"],["אֲחוֹתֵ֑ךְ","H269"],["גָּא֨וֹן","H1347"],["שִׂבְעַת־","H7653"],["לֶ֜חֶם","H3899"],["וְשַׁלְוַ֣ת","H7962"],["הַשְׁקֵ֗ט","H8252"],["הָ֤יָה","H1961"],["לָהּ֙",null],["וְלִבְנוֹתֶ֔יהָ","H1323"],["וְיַד־","H3027"],["עָנִ֥י","H6041"],["וְאֶבְי֖וֹן","H34"],["לֹ֥א","H3808"],["הֶחֱזִֽיקָה׃","H2388"]],"50":[["וַֽתִּגְבְּהֶ֔ינָה","H1361"],["וַתַּעֲשֶׂ֥ינָה","H6213"],["תוֹעֵבָ֖ה","H8441"],["לְפָנָ֑י","H6440"],["וָאָסִ֥יר","H5493"],["אֶתְהֶ֖ן","H853"],["כַּאֲשֶׁ֥ר","H834"],["רָאִֽיתִי׃ס","H7200"]],"51":[["וְשֹׁ֣מְר֔וֹן","H8111"],["כַּחֲצִ֥י","H2677"],["חַטֹּאתַ֖יִךְ","H2403"],["לֹ֣א","H3808"],["חָטָ֑אָה","H2398"],["וַתַּרְבִּ֤י","H7235"],["אֶת־","H853"],["תּוֹעֲבוֹתַ֙יִךְ֙","H8441"],["מֵהֵ֔נָּה",null],["וַתְּצַדְּקִי֙","H6663"],["אֶת־","H853"],["אֲחוֹתֵךְ","H269"],["בְּכָל־","H3605"],["תּוֹעֲבוֹתַ֖יִךְ","H8441"],["אֲשֶׁ֥ר","H834"],["עָשִׂיתי׃","H6213"]],"52":[["גַּם־","H1571"],["אַ֣תְּ׀","H859"],["שְׂאִ֣י","H5375"],["כְלִמָּתֵ֗ךְ","H3639"],["אֲשֶׁ֤ר","H834"],["פִּלַּלְתְּ֙","H6419"],["לַֽאֲחוֹתֵ֔ךְ","H269"],["בְּחַטֹּאתַ֛יִךְ","H2403"],["אֲשֶׁר־","H834"],["הִתְעַ֥בְתְּ","H8581"],["מֵהֵ֖ן",null],["תִּצְדַּ֣קְנָה","H6663"],["מִמֵּ֑ךְ","H4480"],["וְגַם־","H1571"],["אַ֥תְּ","H859"],["בּ֙וֹשִׁי֙","H954"],["וּשְׂאִ֣י","H5375"],["כְלִמָּתֵ֔ךְ","H3639"],["בְּצַדֶּקְתֵּ֖ךְ","H6663"],["אַחְיוֹתֵֽךְ׃","H269"]],"53":[["וְשַׁבְתִּי֙","H7725"],["אֶת־","H853"],["שְׁבִ֣יתְהֶ֔ן","H7622"],["אֶת־","H853"],["שְׁבִית","H7622"],["סְדֹם֙","H5467"],["וּבְנוֹתֶ֔יהָ","H1323"],["וְאֶת־","H853"],["שְׁבִית","H7622"],["שֹׁמְר֖וֹן","H8111"],["וּבְנוֹתֶ֑יהָ","H1323"],["וּשְׁבִית","H7622"],["שְׁבִיתַ֖יִךְ","H7622"],["בְּתוֹכָֽהְנָה׃","H8432"]],"54":[["לְמַ֙עַן֙","H4616"],["תִּשְׂאִ֣י","H5375"],["כְלִמָּתֵ֔ךְ","H3639"],["וְנִכְלַ֕מְתְּ","H3637"],["מִכֹּ֖ל","H3605"],["אֲשֶׁ֣ר","H834"],["עָשִׂ֑ית","H6213"],["בְּנַחֲמֵ֖ךְ","H5162"],["אֹתָֽן׃","H853"]],"55":[["וַאֲחוֹתַ֗יִךְ","H269"],["סְדֹ֤ם","H5467"],["וּבְנוֹתֶ֙יהָ֙","H1323"],["תָּשֹׁ֣בְןָ","H7725"],["לְקַדְמָתָ֔ן","H6927"],["וְשֹֽׁמְרוֹן֙","H8111"],["וּבְנוֹתֶ֔יהָ","H1323"],["תָּשֹׁ֖בְןָ","H7725"],["לְקַדְמָתָ֑ן","H6927"],["וְאַתְּ֙","H859"],["וּבְנוֹתַ֔יִךְ","H1323"],["תְּשֻׁבֶ֖ינָה","H7725"],["לְקַדְמַתְכֶֽן׃","H6927"]],"56":[["וְל֤וֹא","H3808"],["הָֽיְתָה֙","H1961"],["סְדֹ֣ם","H5467"],["אֲחוֹתֵ֔ךְ","H269"],["לִשְׁמוּעָ֖ה","H8052"],["בְּפִ֑יךְ","H6310"],["בְּי֖וֹם","H3117"],["גְּאוֹנָֽיִךְ׃","H1347"]],"57":[["בְּטֶרֶם֮","H2962"],["תִּגָּלֶ֣ה","H1540"],["רָעָתֵךְ֒","H7451"],["כְּמ֗וֹ","H3644"],["עֵ֚ת","H6256"],["חֶרְפַּ֣ת","H2781"],["בְּנוֹת־","H1323"],["אֲרָ֔ם","H758"],["וְכָל־","H3605"],["סְבִיבוֹתֶ֖יהָ","H5439"],["בְּנ֣וֹת","H1323"],["פְּלִשְׁתִּ֑ים","H6430"],["הַשָּׁאט֥וֹת","H7590"],["אוֹתָ֖ךְ","H853"],["מִסָּבִֽיב׃","H5439"]],"58":[["אֶת־","H853"],["זִמָּתֵ֥ךְ","H2154"],["וְאֶת־","H853"],["תּוֹעֲבוֹתַ֖יִךְ","H8441"],["אַ֣תְּ","H859"],["נְשָׂאתִ֑ים","H5375"],["נְאֻ֖ם","H5002"],["יְהוָֽה׃ס","H3068"]],"59":[["כִּ֣י","H3588"],["כֹ֤ה","H3541"],["אָמַר֙","H559"],["אֲדֹנָ֣י","H136"],["יְהוִ֔ה","H3069"],["וְעָשִׂית","H6213"],["אוֹתָ֖ךְ","H854"],["כַּאֲשֶׁ֣ר","H834"],["עָשִׂ֑ית","H6213"],["אֲשֶׁר־","H834"],["בָּזִ֥ית","H959"],["אָלָ֖ה","H423"],["לְהָפֵ֥ר","H6565"],["בְּרִֽית׃","H1285"]],"60":[["וְזָכַרְתִּ֨י","H2142"],["אֲנִ֧י","H589"],["אֶת־","H853"],["בְּרִיתִ֛י","H1285"],["אוֹתָ֖ךְ","H854"],["בִּימֵ֣י","H3117"],["נְעוּרָ֑יִךְ","H5271"],["וַהֲקִמוֹתִ֥י","H6965"],["לָ֖ךְ",null],["בְּרִ֥ית","H1285"],["עוֹלָֽם׃","H5769"]],"61":[["וְזָכַ֣רְתְּ","H2142"],["אֶת־","H853"],["דְּרָכַיִךְ֮","H1870"],["וְנִכְלַמְתְּ֒","H3637"],["בְּקַחְתֵּ֗ךְ","H3947"],["אֶת־","H853"],["אֲחוֹתַ֙יִךְ֙","H269"],["הַגְּדֹל֣וֹת","H1419"],["מִמֵּ֔ךְ","H4480"],["אֶל־","H413"],["הַקְּטַנּ֖וֹת","H6996"],["מִמֵּ֑ךְ","H4480"],["וְנָתַתִּ֨י","H5414"],["אֶתְהֶ֥ן","H853"],["לָ֛ךְ",null],["לְבָנ֖וֹת","H1323"],["וְלֹ֥א","H3808"],["מִבְּרִיתֵֽךְ׃","H1285"]],"62":[["וַהֲקִימוֹתִ֥י","H6965"],["אֲנִ֛י","H589"],["אֶת־","H853"],["בְּרִיתִ֖י","H1285"],["אִתָּ֑ךְ","H854"],["וְיָדַ֖עַתְּ","H3045"],["כִּֽי־","H3588"],["אֲנִ֥י","H589"],["יְהוָֽה׃","H3068"]],"63":[["לְמַ֤עַן","H4616"],["תִּזְכְּרִי֙","H2142"],["וָבֹ֔שְׁתְּ","H954"],["וְלֹ֨א","H3808"],["יִֽהְיֶה־","H1961"],["לָּ֥ךְ",null],["עוֹד֙","H5750"],["פִּתְח֣וֹן","H6610"],["פֶּ֔ה","H6310"],["מִפְּנֵ֖י","H6440"],["כְּלִמָּתֵ֑ךְ","H3639"],["בְּכַפְּרִי־","H3722"],["לָךְ֙",null],["לְכָל־","H3605"],["אֲשֶׁ֣ר","H834"],["עָשִׂ֔ית","H6213"],["נְאֻ֖ם","H5002"],["אֲדֹנָ֥י","H136"],["יְהוִֽה׃ס","H3069"]]}}