{"eng":{"1":[["In the twelfth","H8147"],[". . .","H6240"],["year","H8141"],["on the first","H259"],["day","H2320"],["of the twelfth","H8147"],[". . .","H6240"],["month","H2320"],["the word","H1697"],["of the LORD","H3068"],["came","H1961"],["to me","H413"],["saying","H559"]],"2":[["Son","H1121"],["of man","H120"],["take up","H5375"],["a lament","H7015"],["for","H5921"],["Pharaoh","H6547"],["king","H4428"],["of Egypt","H4714"],["and say","H559"],["to him","H413"],["You are like","H1819"],["a lion","H3715"],["among the nations","H1471"],["you","H859"],["are like a monster","H8577"],["in the seas","H3220"],["You thrash about","H1518"],["in your rivers","H5104"],["churning up","H1804"],["the waters","H4325"],["with your feet","H7272"],["and muddying","H7515"],["the streams","H5104"]],"3":[["This is what","H3541"],["the Lord","H136"],["GOD","H3069"],["says","H559"],["I will spread","H6566"],["My net","H7568"],["over you","H5921"],["-","H853"],["with a company","H6951"],["of many","H7227"],["peoples","H5971"],["and they will draw you up","H5927"],["in My net","H2764"]],"4":[["I will abandon","H5203"],["you on the land","H776"],["and hurl you","H2904"],["into","H5921"],["the open","H6440"],["field","H7704"],["I will cause all","H3605"],["the birds","H5775"],["of the air","H8064"],["to settle","H7931"],["upon you","H5921"],["and all","H3605"],["the beasts","H2416"],["of the earth","H776"],["to eat their fill","H7646"],["of you","H4480"]],"5":[["I will put","H5414"],["-","H853"],["your flesh","H1320"],["on","H5921"],["the mountains","H2022"],["and fill","H4390"],["the valleys","H1516"],["with your remains","H7419"]],"6":[["I will drench","H8248"],["the land","H776"],["with the flow","H6824"],["of your blood","H1818"],["all the way to","H413"],["the mountains","H2022"],["the ravines","H650"],["will be filled","H4390"]],"7":[["When I extinguish you","H3518"],["I will cover","H3680"],["the heavens","H8064"],["and darken","H6937"],["-","H853"],["their stars","H3556"],["I will cover","H3680"],["the sun","H8121"],["with a cloud","H6051"],["and the moon","H3394"],["will not","H3808"],["give its light","H215"],[". . .","H216"]],"8":[["All","H3605"],["the shining","H3974"],["lights","H216"],["in the heavens","H8064"],["I will darken","H6937"],["over you","H5921"],["and I will bring","H5414"],["darkness","H2822"],["upon","H5921"],["your land","H776"],["declares","H5002"],["the Lord","H136"],["GOD","H3069"]],"9":[["I will trouble","H3707"],["the hearts","H3820"],["of many","H7227"],["peoples","H5971"],["when I bring about","H935"],["your destruction","H7667"],["among the nations","H1471"],["in","H5921"],["countries","H776"],["-","H834"],["you do not","H3808"],["know","H3045"]],"10":[["I will cause many","H7227"],["peoples","H5971"],["to be appalled","H8074"],["over you","H5921"],["and their kings","H4428"],["will shudder in horror","H8175"],[". . .","H8178"],["because of you","H5921"],["when I brandish","H5774"],["My sword","H2719"],["before","H5921"],["them","H6440"],["On the day","H3117"],["of your downfall","H4658"],["each of them","H376"],["will tremble","H2729"],["every moment","H7281"],["for his life","H5315"]],"11":[["For","H3588"],["this is what","H3541"],["the Lord","H136"],["GOD","H3069"],["says","H559"],["The sword","H2719"],["of the king","H4428"],["of Babylon","H894"],["will come against you","H935"]],"12":[["I will make your hordes","H1995"],["fall","H5307"],["by the swords","H2719"],["of the mighty","H1368"],["the most ruthless","H6184"],["of all","H3605"],["nations","H1471"],["They will ravage","H7703"],["-","H853"],["the pride","H1347"],["of Egypt","H4714"],["and all","H3605"],["her multitudes","H1995"],["will be destroyed","H8045"]],"13":[["I will slaughter","H6"],["-","H853"],["all","H3605"],["her cattle","H929"],["beside","H5921"],["the abundant","H7227"],["waters","H4325"],["No","H3808"],["human","H120"],["foot","H7272"],["will muddy them","H1804"],["again","H5750"],["and no","H3808"],["cattle","H929"],["hooves","H6541"],["will disturb them","H1804"]],"14":[["Then","H227"],["I will let her waters","H4325"],["settle","H8257"],["and will make her rivers","H5104"],["flow","H1980"],["like oil","H8081"],["declares","H5002"],["the Lord","H136"],["GOD","H3069"]],"15":[["When I make","H5414"],["-","H853"],["the land","H776"],["of Egypt","H4714"],["a desolation","H8077"],["and empty","H8074"],["[it]","H776"],["of all that filled it","H4393"],["when I strike down","H5221"],["-","H853"],["all","H3605"],["who live","H3427"],["there",null],["then they will know","H3045"],["that","H3588"],["I","H589"],["am the LORD","H3068"]],"16":[["This","H1931"],["is the lament","H6969"],["they will chant for her","H7015"],["the daughters","H1323"],["of the nations","H1471"],["will chant it","H6969"],["-","H853"],["Over","H5921"],["Egypt","H4714"],[". . .","H5921"],["and all","H3605"],["her multitudes","H1995"],["they will chant it","H6969"],["-","H853"],["declares","H5002"],["the Lord","H136"],["GOD","H3069"]],"17":[["In the twelfth","H8147"],[". . .","H6240"],["year","H8141"],["on the fifteenth","H2568"],[". . .","H6240"],["day of the month","H2320"],[". . .","H1961"],["the word","H1697"],["of the LORD","H3068"],["came","H1961"],["to me","H413"],["saying","H559"]],"18":[["Son","H1121"],["of man","H120"],["wail","H5091"],["for","H5921"],["the multitudes","H1995"],["of Egypt","H4714"],["and consign","H3381"],["her","H853"],["and the daughters","H1323"],["of the mighty","H117"],["nations","H1471"],["to","H413"],["the depths","H8482"],["of the earth","H776"],["with","H854"],["those who descend","H3381"],["to the Pit","H953"]],"19":[["Whom","H4310"],["do you surpass in beauty","H5276"],["Go down","H3381"],["and be placed","H7901"],["with","H854"],["the uncircumcised","H6189"]],"20":[["They will fall","H5307"],["among","H8432"],["those slain","H2491"],["by the sword","H2719"],["The sword","H2719"],["is appointed","H5414"],["Let [them] drag her away","H4900"],["along with all","H3605"],["-","H853"],["her multitudes","H1995"]],"21":[["Mighty","H1368"],["chiefs","H352"],["will speak","H1696"],["from the midst","H8432"],["of Sheol","H7585"],["about [Egypt]","H854"],["and her allies","H5826"],["They have come down","H3381"],["and lie","H7901"],["with the uncircumcised","H6189"],["with those slain","H2491"],["by the sword","H2719"]],"22":[["Assyria","H804"],["is there","H8033"],["with her whole","H3605"],["company","H6951"],["her graves","H6913"],["are all around her","H5439"],["All of them","H3605"],["are slain","H2491"],["fallen","H5307"],["by the sword","H2719"]],"23":[["Her","H834"],["graves","H6913"],["are set","H5414"],["in the depths","H3411"],["of the Pit","H953"],["and her company","H6951"],["is","H1961"],["all around","H5439"],["her grave","H6900"],["All","H3605"],["of them are slain","H2491"],["fallen","H5307"],["by the sword","H2719"],["those who","H834"],["once spread","H5414"],["terror","H2851"],["in the land","H776"],["of the living","H2416"]],"24":[["Elam","H5867"],["is there","H8033"],["with all","H3605"],["her multitudes","H1995"],["around","H5439"],["her grave","H6900"],["All","H3605"],["of them are slain","H2491"],["fallen","H5307"],["by the sword","H2719"],["those","H834"],["who went down","H3381"],["uncircumcised","H6189"],["to","H413"],["the earth","H776"],["below","H8482"],["who","H834"],["once spread","H5414"],["their terror","H2851"],["in the land","H776"],["of the living","H2416"],["They bear","H5375"],["their disgrace","H3639"],["with","H854"],["those who descend","H3381"],["to the Pit","H953"]],"25":[["Among","H8432"],["the slain","H2491"],["they prepare","H5414"],["a resting place","H4904"],["for [Elam]",null],["with all","H3605"],["her hordes","H1995"],["with her graves","H6913"],["all around her","H5439"],["All","H3605"],["of them are uncircumcised","H6189"],["slain","H2491"],["by the sword","H2719"],["although","H3588"],["their terror","H2851"],["was once spread","H5414"],["in the land","H776"],["of the living","H2416"],["They bear","H5375"],["their disgrace","H3639"],["with","H854"],["those who descend","H3381"],["to the Pit","H953"],["They are placed","H5414"],["among","H8432"],["the slain","H2491"]],"26":[["Meshech","H4902"],["and Tubal","H8422"],["are there","H8033"],["with all","H3605"],["their multitudes","H1995"],["with their graves","H6913"],["all around them","H5439"],["All","H3605"],["of them are uncircumcised","H6189"],["slain","H2490"],["by the sword","H2719"],["because","H3588"],["they spread","H5414"],["their terror","H2851"],["in the land","H776"],["of the living","H2416"]],"27":[["They do not","H3808"],["lie down","H7901"],["with","H854"],["the fallen","H5307"],["warriors","H1368"],["of old","H6189"],["who","H834"],["went down","H3381"],["to Sheol","H7585"],["with their weapons","H3627"],["of war","H4421"],["whose swords","H2719"],["were placed","H5414"],["-","H853"],["under","H8478"],["their heads","H7218"],["whose shields","H5771"],["rested","H1961"],["on","H5921"],["their bones","H6106"],["although","H3588"],["the terror","H2851"],["of the mighty","H1368"],["was once in the land","H776"],["of the living","H2416"]],"28":[["But you too","H859"],["will be shattered","H7665"],["and lie down","H7901"],["among","H8432"],["the uncircumcised","H6189"],["with","H854"],["those slain","H2491"],["by the sword","H2719"]],"29":[["Edom","H123"],["is there","H8033"],["and all","H3605"],["her kings","H4428"],["and princes","H5387"],["who","H834"],["despite their might","H1369"],["are laid","H5414"],["among","H854"],["those slain","H2491"],["by the sword","H2719"],["They","H1992"],["lie down","H7901"],["with","H854"],["the uncircumcised","H6189"],["with","H854"],["those who descend","H3381"],["to the Pit","H953"]],"30":[["All","H3605"],["the leaders","H5257"],["of the north","H6828"],["and all","H3605"],["the Sidonians","H6722"],["are there","H8033"],["they","H834"],["went down","H3381"],["in disgrace","H954"],["with","H854"],["the slain","H2491"],["despite the terror","H2851"],["of their might","H1369"],["They lie","H7901"],["uncircumcised","H6189"],["with","H854"],["those slain","H2491"],["by the sword","H2719"],["and bear","H5375"],["their shame","H3639"],["with","H854"],["those who descend","H3381"],["to the Pit","H953"]],"31":[["-","H853"],["Pharaoh","H6547"],["will see them","H7200"],["and be comforted","H5162"],["over","H5921"],["all","H3605"],["his multitude","H1995"],["Pharaoh","H6547"],["and all","H3605"],["his army","H2428"],["slain","H2491"],["by the sword","H2719"],["declares","H5002"],["the Lord","H136"],["GOD","H3069"]],"32":[["For","H3588"],["I will spread","H5414"],["-","H853"],["My terror","H2851"],["in the land","H776"],["of the living","H2416"],["so that Pharaoh","H6547"],["and all","H3605"],["his multitude","H1995"],["will be laid to rest","H7901"],["among","H8432"],["the uncircumcised","H6189"],["with","H854"],["those slain","H2491"],["by the sword","H2719"],["declares","H5002"],["the Lord","H136"],["GOD","H3069"]]},"heb":{"1":[["וַֽיְהִי֙","H1961"],["בִּשְׁתֵּ֣י","H8147"],["עֶשְׂרֵ֣ה","H6240"],["שָׁנָ֔ה","H8141"],["בִּשְׁנֵי־","H8147"],["עָשָׂ֥ר","H6240"],["חֹ֖דֶשׁ","H2320"],["בְּאֶחָ֣ד","H259"],["לַחֹ֑דֶשׁ","H2320"],["הָיָ֥ה","H1961"],["דְבַר־","H1697"],["יְהוָ֖ה","H3068"],["אֵלַ֥י","H413"],["לֵאמֹֽר׃","H559"]],"2":[["בֶּן־","H1121"],["אָדָ֗ם","H120"],["שָׂ֤א","H5375"],["קִינָה֙","H7015"],["עַל־","H5921"],["פַּרְעֹ֣ה","H6547"],["מֶֽלֶךְ־","H4428"],["מִצְרַ֔יִם","H4714"],["וְאָמַרְתָּ֣","H559"],["אֵלָ֔יו","H413"],["כְּפִ֥יר","H3715"],["גּוֹיִ֖ם","H1471"],["נִדְמֵ֑יתָ","H1819"],["וְאַתָּה֙","H859"],["כַּתַּנִּ֣ים","H8577"],["בַּיַּמִּ֔ים","H3220"],["וַתָּ֣גַח","H1518"],["בְּנַהֲרוֹתֶ֗יךָ","H5104"],["וַתִּדְלַח־","H1804"],["מַ֙יִם֙","H4325"],["בְּרַגְלֶ֔יךָ","H7272"],["וַתִּרְפֹּ֖ס","H7515"],["נַהֲרוֹתָֽם׃","H5104"]],"3":[["כֹּ֤ה","H3541"],["אָמַר֙","H559"],["אֲדֹנָ֣י","H136"],["יְהוִ֔ה","H3069"],["וּפָרַשְׂתִּ֤י","H6566"],["עָלֶ֙יךָ֙","H5921"],["אֶת־","H853"],["רִשְׁתִּ֔י","H7568"],["בִּקְהַ֖ל","H6951"],["עַמִּ֣ים","H5971"],["רַבִּ֑ים","H7227"],["וְהֶעֱל֖וּךָ","H5927"],["בְּחֶרְמִֽי׃","H2764"]],"4":[["וּנְטַשְׁתִּ֣יךָ","H5203"],["בָאָ֔רֶץ","H776"],["עַל־","H5921"],["פְּנֵ֥י","H6440"],["הַשָּׂדֶ֖ה","H7704"],["אֲטִילֶ֑ךָ","H2904"],["וְהִשְׁכַּנְתִּ֤י","H7931"],["עָלֶ֙יךָ֙","H5921"],["כָּל־","H3605"],["ע֣וֹף","H5775"],["הַשָּׁמַ֔יִם","H8064"],["וְהִשְׂבַּעְתִּ֥י","H7646"],["מִמְּךָ֖","H4480"],["חַיַּ֥ת","H2416"],["כָּל־","H3605"],["הָאָֽרֶץ׃","H776"]],"5":[["וְנָתַתִּ֥י","H5414"],["אֶת־","H853"],["בְּשָׂרְךָ֖","H1320"],["עַל־","H5921"],["הֶֽהָרִ֑ים","H2022"],["וּמִלֵּאתִ֥י","H4390"],["הַגֵּאָי֖וֹת","H1516"],["רָמוּתֶֽךָ׃","H7419"]],"6":[["וְהִשְׁקֵיתִ֨י","H8248"],["אֶ֧רֶץ","H776"],["צָפָתְךָ֛","H6824"],["מִדָּמְךָ֖","H1818"],["אֶל־","H413"],["הֶֽהָרִ֑ים","H2022"],["וַאֲפִקִ֖ים","H650"],["יִמָּלְא֥וּן","H4390"],["מִמֶּֽךָּ׃","H4480"]],"7":[["וְכִסֵּיתִ֤י","H3680"],["בְכַבּֽוֹתְךָ֙","H3518"],["שָׁמַ֔יִם","H8064"],["וְהִקְדַּרְתִּ֖י","H6937"],["אֶת־","H853"],["כֹּֽכְבֵיהֶ֑ם","H3556"],["שֶׁ֚מֶשׁ","H8121"],["בֶּעָנָ֣ן","H6051"],["אֲכַסֶּ֔נּוּ","H3680"],["וְיָרֵ֖חַ","H3394"],["לֹא־","H3808"],["יָאִ֥יר","H215"],["אוֹרֽוֹ׃","H216"]],"8":[["כָּל־","H3605"],["מְא֤וֹרֵי","H3974"],["אוֹר֙","H216"],["בַּשָּׁמַ֔יִם","H8064"],["אַקְדִּירֵ֖ם","H6937"],["עָלֶ֑יךָ","H5921"],["וְנָתַ֤תִּי","H5414"],["חֹ֙שֶׁךְ֙","H2822"],["עַֽל־","H5921"],["אַרְצְךָ֔","H776"],["נְאֻ֖ם","H5002"],["אֲדֹנָ֥י","H136"],["יְהוִֽה׃","H3069"]],"9":[["וְהִ֨כְעַסְתִּ֔י","H3707"],["לֵ֖ב","H3820"],["עַמִּ֣ים","H5971"],["רַבִּ֑ים","H7227"],["בַּהֲבִיאִ֤י","H935"],["שִׁבְרְךָ֙","H7667"],["בַּגּוֹיִ֔ם","H1471"],["עַל־","H5921"],["אֲרָצ֖וֹת","H776"],["אֲשֶׁ֥ר","H834"],["לֹֽא־","H3808"],["יְדַעְתָּֽם׃","H3045"]],"10":[["וַהֲשִׁמּוֹתִ֨י","H8074"],["עָלֶ֜יךָ","H5921"],["עַמִּ֣ים","H5971"],["רַבִּ֗ים","H7227"],["וּמַלְכֵיהֶם֙","H4428"],["יִשְׂעֲר֤וּ","H8175"],["עָלֶ֙יךָ֙","H5921"],["שַׂ֔עַר","H8178"],["בְּעוֹפְפִ֥י","H5774"],["חַרְבִּ֖י","H2719"],["עַל־","H5921"],["פְּנֵיהֶ֑ם","H6440"],["וְחָרְד֤וּ","H2729"],["לִרְגָעִים֙","H7281"],["אִ֣ישׁ","H376"],["לְנַפְשׁ֔וֹ","H5315"],["בְּי֖וֹם","H3117"],["מַפַּלְתֶּֽךָ׃ס","H4658"]],"11":[["כִּ֛י","H3588"],["כֹּ֥ה","H3541"],["אָמַ֖ר","H559"],["אֲדֹנָ֣י","H136"],["יְהוִ֑ה","H3069"],["חֶ֥רֶב","H2719"],["מֶֽלֶךְ־","H4428"],["בָּבֶ֖ל","H894"],["תְּבוֹאֶֽךָ׃","H935"]],"12":[["בְּחַרְב֤וֹת","H2719"],["גִּבּוֹרִים֙","H1368"],["אַפִּ֣יל","H5307"],["הֲמוֹנֶ֔ךָ","H1995"],["עָרִיצֵ֥י","H6184"],["גוֹיִ֖ם","H1471"],["כֻּלָּ֑ם","H3605"],["וְשָֽׁדְדוּ֙","H7703"],["אֶת־","H853"],["גְּא֣וֹן","H1347"],["מִצְרַ֔יִם","H4714"],["וְנִשְׁמַ֖ד","H8045"],["כָּל־","H3605"],["הֲמוֹנָֽהּ׃","H1995"]],"13":[["וְהַֽאֲבַדְתִּי֙","H6"],["אֶת־","H853"],["כָּל־","H3605"],["בְּהֶמְתָּ֔הּ","H929"],["מֵעַ֖ל","H5921"],["מַ֣יִם","H4325"],["רַבִּ֑ים","H7227"],["וְלֹ֨א","H3808"],["תִדְלָחֵ֤ם","H1804"],["רֶֽגֶל־","H7272"],["אָדָם֙","H120"],["ע֔וֹד","H5750"],["וּפַרְס֥וֹת","H6541"],["בְּהֵמָ֖ה","H929"],["לֹ֥א","H3808"],["תִדְלָחֵֽם׃","H1804"]],"14":[["אָ֚ז","H227"],["אַשְׁקִ֣יעַ","H8257"],["מֵֽימֵיהֶ֔ם","H4325"],["וְנַהֲרוֹתָ֖ם","H5104"],["כַּשֶּׁ֣מֶן","H8081"],["אוֹלִ֑יךְ","H1980"],["נְאֻ֖ם","H5002"],["אֲדֹנָ֥י","H136"],["יְהוִֽה׃","H3069"]],"15":[["בְּתִתִּי֩","H5414"],["אֶת־","H853"],["אֶ֨רֶץ","H776"],["מִצְרַ֜יִם","H4714"],["שְׁמָמָ֣ה","H8077"],["וּנְשַׁמָּ֗ה","H8074"],["אֶ֚רֶץ","H776"],["מִמְּלֹאָ֔הּ","H4393"],["בְּהַכּוֹתִ֖י","H5221"],["אֶת־","H853"],["כָּל־","H3605"],["י֣וֹשְׁבֵי","H3427"],["בָ֑הּ",null],["וְיָדְע֖וּ","H3045"],["כִּֽי־","H3588"],["אֲנִ֥י","H589"],["יְהוָֽה׃","H3068"]],"16":[["קִינָ֥ה","H7015"],["הִיא֙","H1931"],["וְק֣וֹנְנ֔וּהָ","H6969"],["בְּנ֥וֹת","H1323"],["הַגּוֹיִ֖ם","H1471"],["תְּקוֹנֵ֣נָּה","H6969"],["אוֹתָ֑הּ","H853"],["עַל־","H5921"],["מִצְרַ֤יִם","H4714"],["וְעַל־","H5921"],["כָּל־","H3605"],["הֲמוֹנָהּ֙","H1995"],["תְּקוֹנֵ֣נָּה","H6969"],["אוֹתָ֔הּ","H853"],["נְאֻ֖ם","H5002"],["אֲדֹנָ֥י","H136"],["יְהוִֽה׃פ","H3069"]],"17":[["וַֽיְהִי֙","H1961"],["בִּשְׁתֵּ֣י","H8147"],["עֶשְׂרֵ֣ה","H6240"],["שָׁנָ֔ה","H8141"],["בַּחֲמִשָּׁ֥ה","H2568"],["עָשָׂ֖ר","H6240"],["לַחֹ֑דֶשׁ","H2320"],["הָיָ֥ה","H1961"],["דְבַר־","H1697"],["יְהוָ֖ה","H3068"],["אֵלַ֥י","H413"],["לֵאמֹֽר׃","H559"]],"18":[["בֶּן־","H1121"],["אָדָ֕ם","H120"],["נְהֵ֛ה","H5091"],["עַל־","H5921"],["הֲמ֥וֹן","H1995"],["מִצְרַ֖יִם","H4714"],["וְהוֹרִדֵ֑הוּ","H3381"],["א֠וֹתָהּ","H853"],["וּבְנ֨וֹת","H1323"],["גּוֹיִ֧ם","H1471"],["אַדִּרִ֛ם","H117"],["אֶל־","H413"],["אֶ֥רֶץ","H776"],["תַּחְתִּיּ֖וֹת","H8482"],["אֶת־","H854"],["י֥וֹרְדֵי","H3381"],["בֽוֹר׃","H953"]],"19":[["מִמִּ֖י","H4310"],["נָעָ֑מְתָּ","H5276"],["רְדָ֥ה","H3381"],["וְהָשְׁכְּבָ֖ה","H7901"],["אֶת־","H854"],["עֲרֵלִֽים׃","H6189"]],"20":[["בְּת֥וֹךְ","H8432"],["חַלְלֵי־","H2491"],["חֶ֖רֶב","H2719"],["יִפֹּ֑לוּ","H5307"],["חֶ֣רֶב","H2719"],["נִתָּ֔נָה","H5414"],["מָשְׁכ֥וּ","H4900"],["אוֹתָ֖הּ","H853"],["וְכָל־","H3605"],["הֲמוֹנֶֽיהָ׃","H1995"]],"21":[["יְדַבְּרוּ־","H1696"],["ל֞וֹ",null],["אֵלֵ֧י","H352"],["גִבּוֹרִ֛ים","H1368"],["מִתּ֥וֹךְ","H8432"],["שְׁא֖וֹל","H7585"],["אֶת־","H854"],["עֹֽזְרָ֑יו","H5826"],["יָֽרְד֛וּ","H3381"],["שָׁכְב֥וּ","H7901"],["הָעֲרֵלִ֖ים","H6189"],["חַלְלֵי־","H2491"],["חָֽרֶב׃","H2719"]],"22":[["שָׁ֤ם","H8033"],["אַשּׁוּר֙","H804"],["וְכָל־","H3605"],["קְהָלָ֔הּ","H6951"],["סְבִֽיבוֹתָ֖יו","H5439"],["קִבְרֹתָ֑יו","H6913"],["כֻּלָּ֣ם","H3605"],["חֲלָלִ֔ים","H2491"],["הַנֹּפְלִ֖ים","H5307"],["בֶּחָֽרֶב׃","H2719"]],"23":[["אֲשֶׁ֨ר","H834"],["נִתְּנ֤וּ","H5414"],["קִבְרֹתֶ֙יהָ֙","H6913"],["בְּיַרְכְּתֵי־","H3411"],["ב֔וֹר","H953"],["וַיְהִ֣י","H1961"],["קְהָלָ֔הּ","H6951"],["סְבִיב֖וֹת","H5439"],["קְבֻרָתָ֑הּ","H6900"],["כֻּלָּ֤ם","H3605"],["חֲלָלִים֙","H2491"],["נֹפְלִ֣ים","H5307"],["בַּחֶ֔רֶב","H2719"],["אֲשֶׁר־","H834"],["נָתְנ֥וּ","H5414"],["חִתִּ֖ית","H2851"],["בְּאֶ֥רֶץ","H776"],["חַיִּֽים׃","H2416"]],"24":[["שָׁ֤ם","H8033"],["עֵילָם֙","H5867"],["וְכָל־","H3605"],["הֲמוֹנָ֔הּ","H1995"],["סְבִיב֖וֹת","H5439"],["קְבֻרָתָ֑הּ","H6900"],["כֻּלָּ֣ם","H3605"],["חֲלָלִים֩","H2491"],["הַנֹּפְלִ֨ים","H5307"],["בַּחֶ֜רֶב","H2719"],["אֲ‍ֽשֶׁר־","H834"],["יָרְד֥וּ","H3381"],["עֲרֵלִ֣ים׀","H6189"],["אֶל־","H413"],["אֶ֣רֶץ","H776"],["תַּחְתִּיּ֗וֹת","H8482"],["אֲשֶׁ֨ר","H834"],["נָתְנ֤וּ","H5414"],["חִתִּיתָם֙","H2851"],["בְּאֶ֣רֶץ","H776"],["חַיִּ֔ים","H2416"],["וַיִּשְׂא֥וּ","H5375"],["כְלִמָּתָ֖ם","H3639"],["אֶת־","H854"],["י֥וֹרְדֵי","H3381"],["בֽוֹר׃","H953"]],"25":[["בְּת֣וֹךְ","H8432"],["חֲ֠לָלִים","H2491"],["נָתְנ֨וּ","H5414"],["מִשְׁכָּ֥ב","H4904"],["לָהּ֙",null],["בְּכָל־","H3605"],["הֲמוֹנָ֔הּ","H1995"],["סְבִֽיבוֹתָ֖יו","H5439"],["קִבְרֹתֶ֑הָ","H6913"],["כֻּלָּ֣ם","H3605"],["עֲרֵלִ֣ים","H6189"],["חַלְלֵי־","H2491"],["חֶ֡רֶב","H2719"],["כִּֽי־","H3588"],["נִתַּ֨ן","H5414"],["חִתִּיתָ֜ם","H2851"],["בְּאֶ֣רֶץ","H776"],["חַיִּ֗ים","H2416"],["וַיִּשְׂא֤וּ","H5375"],["כְלִמָּתָם֙","H3639"],["אֶת־","H854"],["י֣וֹרְדֵי","H3381"],["ב֔וֹר","H953"],["בְּת֥וֹךְ","H8432"],["חֲלָלִ֖ים","H2491"],["נִתָּֽן׃","H5414"]],"26":[["שָׁ֣ם","H8033"],["מֶ֤שֶׁךְ","H4902"],["תֻּבַל֙","H8422"],["וְכָל־","H3605"],["הֲמוֹנָ֔הּ","H1995"],["סְבִֽיבוֹתָ֖יו","H5439"],["קִבְרוֹתֶ֑יהָ","H6913"],["כֻּלָּ֤ם","H3605"],["עֲרֵלִים֙","H6189"],["מְחֻ֣לְלֵי","H2490"],["חֶ֔רֶב","H2719"],["כִּֽי־","H3588"],["נָתְנ֥וּ","H5414"],["חִתִּיתָ֖ם","H2851"],["בְּאֶ֥רֶץ","H776"],["חַיִּֽים׃","H2416"]],"27":[["וְלֹ֤א","H3808"],["יִשְׁכְּבוּ֙","H7901"],["אֶת־","H854"],["גִּבּוֹרִ֔ים","H1368"],["נֹפְלִ֖ים","H5307"],["מֵעֲרֵלִ֑ים","H6189"],["אֲשֶׁ֣ר","H834"],["יָרְדֽוּ־","H3381"],["שְׁא֣וֹל","H7585"],["בִּכְלֵֽי־","H3627"],["מִלְחַמְתָּם֩","H4421"],["וַיִּתְּנ֨וּ","H5414"],["אֶת־","H853"],["חַרְבוֹתָ֜ם","H2719"],["תַּ֣חַת","H8478"],["רָאשֵׁיהֶ֗ם","H7218"],["וַתְּהִ֤י","H1961"],["עֲוֺֽנֹתָם֙","H5771"],["עַל־","H5921"],["עַצְמוֹתָ֔ם","H6106"],["כִּֽי־","H3588"],["חִתִּ֥ית","H2851"],["גִּבּוֹרִ֖ים","H1368"],["בְּאֶ֥רֶץ","H776"],["חַיִּֽים׃","H2416"]],"28":[["וְאַתָּ֗ה","H859"],["בְּת֧וֹךְ","H8432"],["עֲרֵלִ֛ים","H6189"],["תִּשָּׁבַ֥ר","H7665"],["וְתִשְׁכַּ֖ב","H7901"],["אֶת־","H854"],["חַלְלֵי־","H2491"],["חָֽרֶב׃","H2719"]],"29":[["שָׁ֣מָּה","H8033"],["אֱד֗וֹם","H123"],["מְלָכֶ֙יהָ֙","H4428"],["וְכָל־","H3605"],["נְשִׂיאֶ֔יהָ","H5387"],["אֲשֶׁר־","H834"],["נִתְּנ֥וּ","H5414"],["בִגְבוּרָתָ֖ם","H1369"],["אֶת־","H854"],["חַלְלֵי־","H2491"],["חָ֑רֶב","H2719"],["הֵ֛מָּה","H1992"],["אֶת־","H854"],["עֲרֵלִ֥ים","H6189"],["יִשְׁכָּ֖בוּ","H7901"],["וְאֶת־","H854"],["יֹ֥רְדֵי","H3381"],["בֽוֹר׃","H953"]],"30":[["שָׁ֣מָּה","H8033"],["נְסִיכֵ֥י","H5257"],["צָפ֛וֹן","H6828"],["כֻּלָּ֖ם","H3605"],["וְכָל־","H3605"],["צִֽדֹנִ֑י","H6722"],["אֲשֶׁר־","H834"],["יָרְד֣וּ","H3381"],["אֶת־","H854"],["חֲלָלִ֗ים","H2491"],["בְּחִתִּיתָ֤ם","H2851"],["מִגְבֽוּרָתָם֙","H1369"],["בּוֹשִׁ֔ים","H954"],["וַיִּשְׁכְּב֤וּ","H7901"],["עֲרֵלִים֙","H6189"],["אֶת־","H854"],["חַלְלֵי־","H2491"],["חֶ֔רֶב","H2719"],["וַיִּשְׂא֥וּ","H5375"],["כְלִמָּתָ֖ם","H3639"],["אֶת־","H854"],["י֥וֹרְדֵי","H3381"],["בֽוֹר׃","H953"]],"31":[["אוֹתָם֙","H853"],["יִרְאֶ֣ה","H7200"],["פַרְעֹ֔ה","H6547"],["וְנִחַ֖ם","H5162"],["עַל־","H5921"],["כָּל־","H3605"],["הֲמוֹנֹה","H1995"],["חַלְלֵי־","H2491"],["חֶ֙רֶב֙","H2719"],["פַּרְעֹ֣ה","H6547"],["וְכָל־","H3605"],["חֵיל֔וֹ","H2428"],["נְאֻ֖ם","H5002"],["אֲדֹנָ֥י","H136"],["יְהוִֽה׃","H3069"]],"32":[["כִּֽי־","H3588"],["נָתַ֥תִּי","H5414"],["אֶת־","H853"],["חִתִּיתוֹ","H2851"],["בְּאֶ֣רֶץ","H776"],["חַיִּ֑ים","H2416"],["וְהֻשְׁכַּב֩","H7901"],["בְּת֨וֹךְ","H8432"],["עֲרֵלִ֜ים","H6189"],["אֶת־","H854"],["חַלְלֵי־","H2491"],["חֶ֗רֶב","H2719"],["פַּרְעֹה֙","H6547"],["וְכָל־","H3605"],["הֲמוֹנֹ֔ה","H1995"],["נְאֻ֖ם","H5002"],["אֲדֹנָ֥י","H136"],["יְהוִֽה׃פ","H3069"]]}}