{
  "KUSTBLN2DA": {
    "43": {
      "2": {
        "1": [
          2.06,
          7.06
        ],
        "11": [
          81.964,
          92.735
        ],
        "12": [
          92.735,
          98.145
        ],
        "13": [
          98.145,
          104.526
        ],
        "14": [
          104.526,
          117.906
        ],
        "15": [
          117.906,
          124.407
        ],
        "16": [
          124.407,
          129.367
        ],
        "17": [
          129.367,
          147.508
        ],
        "2": [
          7.06,
          14.451
        ],
        "22": [
          175.959,
          191.8
        ],
        "23": [
          191.8,
          202.511
        ],
        "24": [
          202.511,
          207.821
        ],
        "27": [
          224.242,
          230.612
        ],
        "3": [
          14.451,
          20.331
        ],
        "32": [
          268.164,
          275.835
        ],
        "33": [
          275.835,
          287.205
        ],
        "36": [
          300.666,
          313.057
        ],
        "37": [
          313.057,
          322.487
        ],
        "38": [
          322.487,
          335.368
        ],
        "4": [
          20.331,
          28.031
        ],
        "41": [
          352.789,
          359.839
        ],
        "42": [
          359.839,
          368.52
        ],
        "43": [
          368.52,
          375.26
        ],
        "44": [
          375.26,
          382.1
        ],
        "45": [
          382.1,
          388.331
        ],
        "46": [
          388.331,
          396.581
        ],
        "47": [
          396.581,
          396.581
        ],
        "5": [
          28.031,
          36.382
        ],
        "6": [
          36.382,
          45.592
        ],
        "7": [
          45.592,
          52.563
        ],
        "8": [
          52.563,
          57.713
        ]
      }
    }
  },
  "KUSTBLN2SA": {
    "43": {
      "1": {
        "12": [
          100.549,
          105.97
        ],
        "13": [
          105.97,
          126.172
        ],
        "14": [
          126.172,
          135.053
        ]
      },
      "2": {
        "1": [
          2.06,
          7.06
        ],
        "11": [
          81.964,
          92.735
        ],
        "12": [
          92.735,
          98.145
        ],
        "13": [
          98.145,
          104.526
        ],
        "14": [
          104.526,
          117.906
        ],
        "15": [
          117.906,
          124.407
        ],
        "16": [
          124.407,
          129.367
        ],
        "17": [
          129.367,
          147.508
        ],
        "2": [
          7.06,
          14.451
        ],
        "22": [
          175.959,
          191.8
        ],
        "23": [
          191.8,
          202.511
        ],
        "24": [
          202.511,
          207.821
        ],
        "27": [
          224.242,
          230.612
        ],
        "3": [
          14.451,
          20.331
        ],
        "32": [
          268.164,
          275.835
        ],
        "33": [
          275.835,
          287.205
        ],
        "36": [
          300.666,
          313.057
        ],
        "37": [
          313.057,
          322.487
        ],
        "38": [
          322.487,
          335.368
        ],
        "4": [
          20.331,
          28.031
        ],
        "41": [
          352.789,
          359.839
        ],
        "42": [
          359.839,
          368.52
        ],
        "43": [
          368.52,
          375.26
        ],
        "44": [
          375.26,
          382.1
        ],
        "45": [
          382.1,
          388.331
        ],
        "46": [
          388.331,
          396.581
        ],
        "47": [
          396.581,
          396.581
        ],
        "5": [
          28.031,
          36.382
        ],
        "6": [
          36.382,
          45.592
        ],
        "7": [
          45.592,
          52.563
        ],
        "8": [
          52.563,
          57.713
        ]
      }
    }
  }
}