{
  "CJOWBTN1DA": {
    "24": {
      "1": {
        "29": [
          454.53,
          490.6
        ],
        "32-34": [
          531.73,
          568.28,
          581.01
        ]
      }
    },
    "48": {
      "1": {
        "29": [
          454.53,
          490.6
        ]
      }
    }
  },
  "warnings": {
    "CJOWBTN1DA": {
      "24": {
        "1": {
          "32-34": {
            "details": "verse 32 missing, timestamps repeated",
            "missing_verses": [
              32
            ],
            "type": "partial"
          }
        }
      }
    }
  }
}