{
  "BTDLAIN1DA": {
    "6": {
      "2": {
        "1": [
          3.94,
          11.07
        ],
        "2": [
          11.07,
          20.951
        ],
        "3": [
          20.951,
          28.571
        ],
        "4": [
          28.571,
          40.142
        ]
      },
      "9": {
        "3": [
          26.001,
          35.382
        ],
        "4": [
          35.382,
          44.502
        ],
        "5": [
          44.502,
          53.352
        ],
        "6": [
          53.352,
          60.993
        ]
      }
    }
  }
}