{
  "PADTBLN2DA": {
    "3": {
      "1": {
        "40": [
          760.76,
          785.09
        ],
        "41": [
          785.09,
          798.04
        ],
        "42": [
          798.04,
          806.25
        ]
      },
      "2": {
        "1": [
          3.07,
          14.51
        ],
        "10": [
          142.03,
          153.15
        ],
        "11": [
          153.15,
          164.02
        ],
        "12": [
          164.02,
          188.13
        ],
        "2": [
          14.51,
          36.08
        ],
        "3": [
          36.08,
          46.75
        ],
        "4": [
          46.75,
          78.61
        ],
        "5": [
          78.61,
          99.36
        ],
        "6": [
          99.36,
          110.48
        ],
        "7": [
          110.48,
          120.45
        ],
        "8": [
          120.45,
          130.17
        ],
        "9": [
          130.17,
          142.03
        ]
      }
    }
  },
  "PADTBLN2SA": {
    "3": {
      "1": {
        "40": [
          760.76,
          785.09
        ],
        "41": [
          785.09,
          798.04
        ],
        "42": [
          798.04,
          806.25
        ]
      }
    }
  }
}