{"eng":{"1":[["A Psalm","H4210"],["A song","H7892"],["for the Sabbath","H7676"],["day","H3117"],["It is good","H2896"],["to praise","H3034"],["the LORD","H3068"],["and to sing praises","H2167"],["to Your name","H8034"],["O Most High","H5945"]],"2":[["to proclaim","H5046"],["Your loving devotion","H2617"],["in the morning","H1242"],["and Your faithfulness","H530"],["at night","H3915"]],"3":[["with","H5921"],["the ten-stringed","H6218"],[". . .","H5921"],["harp","H5035"],[". . .","H5921"],["and the melody","H1902"],["of the lyre","H3658"]],"4":[["For","H3588"],["You, O LORD","H3068"],["have made me glad","H8055"],["by Your deeds","H6467"],["I sing for joy","H7442"],["at the works","H4639"],["of Your hands","H3027"]],"5":[["How","H4100"],["great","H1431"],["are Your works","H4639"],["O LORD","H3068"],["how","H3966"],["deep","H6009"],["are Your thoughts","H4284"]],"6":[["A senseless","H1198"],["man","H376"],["does not","H3808"],["know","H3045"],["and a fool","H3684"],["does not","H3808"],["understand","H995"],["-","H853"]],"7":[["that though the wicked","H7563"],["sprout","H6524"],["like","H3644"],["grass","H6212"],["and all","H3605"],["evildoers","H6466"],[". . .","H205"],["flourish","H6692"],["they will be","H5704"],["forever","H5703"],["destroyed","H8045"]],"8":[["But You","H859"],["O LORD","H3068"],["are exalted forever","H4791"],[". . .","H5769"]],"9":[["For","H3588"],["surely","H2009"],["Your enemies","H341"],["O LORD","H3068"],["vvv","H3588"],["surely","H2009"],["Your enemies","H341"],["will perish","H6"],["all","H3605"],["evildoers","H6466"],[". . .","H205"],["will be scattered","H6504"]],"10":[["But You have exalted","H7311"],["my horn","H7161"],["like that of a wild ox","H7214"],["with fine","H7488"],["oil","H8081"],["I have been anointed","H1101"]],"11":[["My eyes","H5869"],["see the downfall","H5027"],["of my enemies","H7790"],["my ears","H241"],["hear","H8085"],["the wailing","H6965"],["of my wicked","H7489"],["foes","H5921"]],"12":[["The righteous","H6662"],["will flourish","H6524"],["like a palm tree","H8558"],["and grow","H7685"],["like a cedar","H730"],["in Lebanon","H3844"]],"13":[["Planted","H8362"],["in the house","H1004"],["of the LORD","H3068"],["they will flourish","H6524"],["in the courts","H2691"],["of our God","H430"]],"14":[["In old age","H7872"],["they will still","H5750"],["bear fruit","H5107"],["healthy","H1879"],["and green","H7488"],["they will remain","H1961"]],"15":[["to proclaim","H5046"],[". . .","H3588"],["The LORD","H3068"],["[is] upright","H3477"],["He is my Rock","H6697"],["and in Him",null],["there is no","H3808"],["unrighteousness","H5766"]]},"heb":{"1":[["מִזְמ֥וֹר","H4210"],["שִׁ֗יר","H7892"],["לְי֣וֹם","H3117"],["הַשַּׁבָּֽת׃","H7676"],["ט֗וֹב","H2896"],["לְהֹד֥וֹת","H3034"],["לַיהוָ֑ה","H3068"],["וּלְזַמֵּ֖ר","H2167"],["לְשִׁמְךָ֣","H8034"],["עֶלְיֽוֹן׃","H5945"]],"2":[["לְהַגִּ֣יד","H5046"],["בַּבֹּ֣קֶר","H1242"],["חַסְֽדֶּ֑ךָ","H2617"],["וֶ֝אֱמֽוּנָתְךָ֗","H530"],["בַּלֵּילֽוֹת׃","H3915"]],"3":[["עֲ‍ֽלֵי־","H5921"],["עָ֭שׂוֹר","H6218"],["וַעֲלֵי־","H5921"],["נָ֑בֶל","H5035"],["עֲלֵ֖י","H5921"],["הִגָּי֣וֹן","H1902"],["בְּכִנּֽוֹר׃","H3658"]],"4":[["כִּ֤י","H3588"],["שִׂמַּחְתַּ֣נִי","H8055"],["יְהוָ֣ה","H3068"],["בְּפָעֳלֶ֑ךָ","H6467"],["בְּֽמַעֲשֵׂ֖י","H4639"],["יָדֶ֣יךָ","H3027"],["אֲרַנֵּֽן׃","H7442"]],"5":[["מַה־","H4100"],["גָּדְל֣וּ","H1431"],["מַעֲשֶׂ֣יךָ","H4639"],["יְהוָ֑ה","H3068"],["מְ֝אֹ֗ד","H3966"],["עָמְק֥וּ","H6009"],["מַחְשְׁבֹתֶֽיךָ׃","H4284"]],"6":[["אִֽישׁ־","H376"],["בַּ֭עַר","H1198"],["לֹ֣א","H3808"],["יֵדָ֑ע","H3045"],["וּ֝כְסִ֗יל","H3684"],["לֹא־","H3808"],["יָבִ֥ין","H995"],["אֶת־","H853"],["זֹֽאת׃","H2063"]],"7":[["בִּפְרֹ֤חַ","H6524"],["רְשָׁעִ֨ים׀","H7563"],["כְּמ֥וֹ","H3644"],["עֵ֗שֶׂב","H6212"],["וַ֭יָּצִיצוּ","H6692"],["כָּל־","H3605"],["פֹּ֣עֲלֵי","H6466"],["אָ֑וֶן","H205"],["לְהִשָּֽׁמְדָ֥ם","H8045"],["עֲדֵי־","H5703"],["עַֽד׃","H5704"]],"8":[["וְאַתָּ֥ה","H859"],["מָר֗וֹם","H4791"],["לְעֹלָ֥ם","H5769"],["יְהוָֽה׃","H3068"]],"9":[["כִּ֤י","H3588"],["הִנֵּ֪ה","H2009"],["אֹיְבֶ֡יךָ׀","H341"],["יְֽהוָ֗ה","H3068"],["כִּֽי־","H3588"],["הִנֵּ֣ה","H2009"],["אֹיְבֶ֣יךָ","H341"],["יֹאבֵ֑דוּ","H6"],["יִ֝תְפָּרְד֗וּ","H6504"],["כָּל־","H3605"],["פֹּ֥עֲלֵי","H6466"],["אָֽוֶן׃","H205"]],"10":[["וַתָּ֣רֶם","H7311"],["כִּרְאֵ֣ים","H7214"],["קַרְנִ֑י","H7161"],["בַּ֝לֹּתִ֗י","H1101"],["בְּשֶׁ֣מֶן","H8081"],["רַעֲנָֽן׃","H7488"]],"11":[["וַתַּבֵּ֥ט","H5027"],["עֵינִ֗י","H5869"],["בְּשׁ֫וּרָ֥י","H7790"],["בַּקָּמִ֖ים","H6965"],["עָלַ֥י","H5921"],["מְרֵעִ֗ים","H7489"],["תִּשְׁמַ֥עְנָה","H8085"],["אָזְנָֽי׃","H241"]],"12":[["צַ֭דִּיק","H6662"],["כַּתָּמָ֣ר","H8558"],["יִפְרָ֑ח","H6524"],["כְּאֶ֖רֶז","H730"],["בַּלְּבָנ֣וֹן","H3844"],["יִשְׂגֶּֽה׃","H7685"]],"13":[["שְׁ֭תוּלִים","H8362"],["בְּבֵ֣ית","H1004"],["יְהוָ֑ה","H3068"],["בְּחַצְר֖וֹת","H2691"],["אֱלֹהֵ֣ינוּ","H430"],["יַפְרִֽיחוּ׃","H6524"]],"14":[["ע֭וֹד","H5750"],["יְנוּב֣וּן","H5107"],["בְּשֵׂיבָ֑ה","H7872"],["דְּשֵׁנִ֖ים","H1879"],["וְרַֽעֲנַנִּ֣ים","H7488"],["יִהְיֽוּ׃","H1961"]],"15":[["לְ֭הַגִּיד","H5046"],["כִּֽי־","H3588"],["יָשָׁ֣ר","H3477"],["יְהוָ֑ה","H3068"],["צ֝וּרִ֗י","H6697"],["וְֽלֹא־","H3808"],["עֹלָתָה","H5766"],["בּֽוֹ׃",null]]}}