{
  "KFXBIVN1DA": {
    "1": {
      "1": {
        "1": [
          5.92,
          15.52
        ],
        "10": [
          72.422,
          81.842
        ],
        "11": [
          81.842,
          87.912
        ],
        "12": [
          87.912,
          97.512
        ],
        "13": [
          97.512,
          109.412
        ],
        "14": [
          109.412,
          125.453
        ],
        "15": [
          125.453,
          141.703
        ],
        "16": [
          141.703,
          151.433
        ],
        "17": [
          151.433,
          159.693
        ],
        "18": [
          159.693,
          169.214
        ],
        "19": [
          169.214,
          184.614
        ],
        "2": [
          15.52,
          19.0
        ],
        "20": [
          184.614,
          193.164
        ],
        "21": [
          193.164,
          204.894
        ],
        "22": [
          204.894,
          217.225
        ],
        "23": [
          217.225,
          233.745
        ],
        "24": [
          233.745,
          240.195
        ],
        "25": [
          240.195,
          250.685
        ],
        "26": [
          250.685,
          262.846
        ],
        "27": [
          262.846,
          274.646
        ],
        "28": [
          274.646,
          285.736
        ],
        "29": [
          285.736,
          298.756
        ],
        "3": [
          19.0,
          28.361
        ],
        "30": [
          298.756,
          311.197
        ],
        "31": [
          311.197,
          322.527
        ],
        "32": [
          322.527,
          333.467
        ],
        "33": [
          333.467,
          354.098
        ],
        "34": [
          354.098,
          362.598
        ],
        "35": [
          362.598,
          368.898
        ],
        "36": [
          368.898,
          375.848
        ],
        "37": [
          375.848,
          383.018
        ],
        "38": [
          383.018,
          397.328
        ],
        "39": [
          397.328,
          412.369
        ],
        "4": [
          28.361,
          33.771
        ],
        "40": [
          412.369,
          423.949
        ],
        "41": [
          423.949,
          435.719
        ],
        "42": [
          435.719,
          451.33
        ],
        "43": [
          451.33,
          461.21
        ],
        "44": [
          461.21,
          469.09
        ],
        "45": [
          469.09,
          488.77
        ],
        "46": [
          488.77,
          498.891
        ],
        "47": [
          498.891,
          511.241
        ],
        "48": [
          511.241,
          525.361
        ],
        "49": [
          525.361,
          534.231
        ],
        "5": [
          33.771,
          41.741
        ],
        "50": [
          534.231,
          547.902
        ],
        "51": [
          547.902,
          547.902
        ],
        "6": [
          41.741,
          48.791
        ],
        "7": [
          48.791,
          58.901
        ],
        "8": [
          58.901,
          65.361
        ],
        "9": [
          65.361,
          72.422
        ]
      }
    },
    "10": {
      "10": {
        "1": [
          4.76,
          16.351
        ],
        "10": [
          97.585,
          110.996
        ],
        "11": [
          110.996,
          117.937
        ],
        "12": [
          117.937,
          134.637
        ],
        "13": [
          134.637,
          143.428
        ],
        "14": [
          143.428,
          150.998
        ],
        "15": [
          150.998,
          161.049
        ],
        "16": [
          161.049,
          174.31
        ],
        "17": [
          174.31,
          182.71
        ],
        "18": [
          182.71,
          199.691
        ],
        "19": [
          199.691,
          204.781
        ],
        "2": [
          16.351,
          22.021
        ],
        "20": [
          204.781,
          213.432
        ],
        "21": [
          213.432,
          222.282
        ],
        "22": [
          222.282,
          228.573
        ],
        "23": [
          228.573,
          235.713
        ],
        "24": [
          235.713,
          251.804
        ],
        "25": [
          251.804,
          264.965
        ],
        "26": [
          264.965,
          272.775
        ],
        "27": [
          272.775,
          281.136
        ],
        "28": [
          281.136,
          292.556
        ],
        "29": [
          292.556,
          303.127
        ],
        "3": [
          22.021,
          35.822
        ],
        "30": [
          303.127,
          306.997
        ],
        "31": [
          306.997,
          312.937
        ],
        "32": [
          312.937,
          326.168
        ],
        "33": [
          326.168,
          342.559
        ],
        "34": [
          342.559,
          350.229
        ],
        "35": [
          350.229,
          358.06
        ],
        "36": [
          358.06,
          371.941
        ],
        "37": [
          371.941,
          379.581
        ],
        "38": [
          379.581,
          398.952
        ],
        "39": [
          398.952,
          405.252
        ],
        "4": [
          35.822,
          49.623
        ],
        "40": [
          405.252,
          414.703
        ],
        "41": [
          414.703,
          427.924
        ],
        "42": [
          427.924,
          427.924
        ],
        "5": [
          49.623,
          58.813
        ],
        "6": [
          58.813,
          68.614
        ],
        "7": [
          68.614,
          75.814
        ],
        "8": [
          75.814,
          84.195
        ],
        "9": [
          84.195,
          97.585
        ]
      }
    },
    "11": {
      "11": {
        "1": [
          3.63,
          15.24
        ],
        "10": [
          101.763,
          109.153
        ],
        "11": [
          109.153,
          120.863
        ],
        "12": [
          120.863,
          127.933
        ],
        "13": [
          127.933,
          136.933
        ],
        "14": [
          136.933,
          141.974
        ],
        "15": [
          141.974,
          154.334
        ],
        "16": [
          154.334,
          166.674
        ],
        "17": [
          166.674,
          176.374
        ],
        "18": [
          176.374,
          184.125
        ],
        "19": [
          184.125,
          193.535
        ],
        "2": [
          15.24,
          27.321
        ],
        "20": [
          193.535,
          203.375
        ],
        "21": [
          203.375,
          212.205
        ],
        "22": [
          212.205,
          221.186
        ],
        "23": [
          221.186,
          225.716
        ],
        "24": [
          225.716,
          235.746
        ],
        "25": [
          235.746,
          249.126
        ],
        "26": [
          249.126,
          260.366
        ],
        "27": [
          260.366,
          272.127
        ],
        "28": [
          272.127,
          284.977
        ],
        "29": [
          284.977,
          292.117
        ],
        "3": [
          27.321,
          38.621
        ],
        "30": [
          292.117,
          298.917
        ],
        "31": [
          298.917,
          319.488
        ],
        "32": [
          319.488,
          334.188
        ],
        "33": [
          334.188,
          348.379
        ],
        "34": [
          348.379,
          355.759
        ],
        "35": [
          355.759,
          358.519
        ],
        "36": [
          358.519,
          366.269
        ],
        "37": [
          366.269,
          376.829
        ],
        "38": [
          376.829,
          388.02
        ],
        "39": [
          388.02,
          404.33
        ],
        "4": [
          38.621,
          52.891
        ],
        "40": [
          404.33,
          413.4
        ],
        "41": [
          413.4,
          429.541
        ],
        "42": [
          429.541,
          445.601
        ],
        "43": [
          445.601,
          453.201
        ],
        "44": [
          453.201,
          471.722
        ],
        "45": [
          471.722,
          484.732
        ],
        "46": [
          484.732,
          492.962
        ],
        "47": [
          492.962,
          506.683
        ],
        "48": [
          506.683,
          521.923
        ],
        "49": [
          521.923,
          534.853
        ],
        "5": [
          52.891,
          58.771
        ],
        "50": [
          534.853,
          548.454
        ],
        "51": [
          548.454,
          562.504
        ],
        "52": [
          562.504,
          573.264
        ],
        "53": [
          573.264,
          580.514
        ],
        "54": [
          580.514,
          601.385
        ],
        "55": [
          601.385,
          615.635
        ],
        "56": [
          615.635,
          629.626
        ],
        "57": [
          629.626,
          629.626
        ],
        "6": [
          58.771,
          68.512
        ],
        "7": [
          68.512,
          74.962
        ],
        "8": [
          74.962,
          89.352
        ],
        "9": [
          89.352,
          101.763
        ]
      }
    },
    "12": {
      "12": {
        "1": [
          2.41,
          17.38
        ],
        "10": [
          124.482,
          129.902
        ],
        "11": [
          129.902,
          139.762
        ],
        "12": [
          139.762,
          149.052
        ],
        "13": [
          149.052,
          166.732
        ],
        "14": [
          166.732,
          173.662
        ],
        "15": [
          173.662,
          186.112
        ],
        "16": [
          186.112,
          204.583
        ],
        "17": [
          204.583,
          218.063
        ],
        "18": [
          218.063,
          228.413
        ],
        "19": [
          228.413,
          241.273
        ],
        "2": [
          17.38,
          29.95
        ],
        "20": [
          241.273,
          249.503
        ],
        "21": [
          249.503,
          263.473
        ],
        "22": [
          263.473,
          275.244
        ],
        "23": [
          275.244,
          281.604
        ],
        "24": [
          281.604,
          298.214
        ],
        "25": [
          298.214,
          313.134
        ],
        "26": [
          313.134,
          331.024
        ],
        "27": [
          331.024,
          346.984
        ],
        "28": [
          346.984,
          358.575
        ],
        "29": [
          358.575,
          372.665
        ],
        "3": [
          29.95,
          52.001
        ],
        "30": [
          372.665,
          378.515
        ],
        "31": [
          378.515,
          387.875
        ],
        "32": [
          387.875,
          396.825
        ],
        "33": [
          396.825,
          402.645
        ],
        "34": [
          402.645,
          419.455
        ],
        "35": [
          419.455,
          440.166
        ],
        "36": [
          440.166,
          456.006
        ],
        "37": [
          456.006,
          464.626
        ],
        "38": [
          464.626,
          479.716
        ],
        "39": [
          479.716,
          485.716
        ],
        "4": [
          52.001,
          63.631
        ],
        "40": [
          485.716,
          505.196
        ],
        "41": [
          505.196,
          513.627
        ],
        "42": [
          513.627,
          534.357
        ],
        "43": [
          534.357,
          543.087
        ],
        "44": [
          543.087,
          554.197
        ],
        "45": [
          554.197,
          560.667
        ],
        "46": [
          560.667,
          569.617
        ],
        "47": [
          569.617,
          584.397
        ],
        "48": [
          584.397,
          597.658
        ],
        "49": [
          597.658,
          610.398
        ],
        "5": [
          63.631,
          71.151
        ],
        "50": [
          610.398,
          610.398
        ],
        "6": [
          71.151,
          90.171
        ],
        "7": [
          90.171,
          100.471
        ],
        "8": [
          100.471,
          108.201
        ],
        "9": [
          108.201,
          124.482
        ]
      }
    },
    "13": {
      "13": {
        "1": [
          4.01,
          26.491
        ],
        "10": [
          122.745,
          134.565
        ],
        "11": [
          134.565,
          147.766
        ],
        "12": [
          147.766,
          162.427
        ],
        "13": [
          162.427,
          171.577
        ],
        "14": [
          171.577,
          184.117
        ],
        "15": [
          184.117,
          194.508
        ],
        "16": [
          194.508,
          206.948
        ],
        "17": [
          206.948,
          214.819
        ],
        "18": [
          214.819,
          237.47
        ],
        "19": [
          237.47,
          254.0
        ],
        "2": [
          26.491,
          40.762
        ],
        "20": [
          254.0,
          267.811
        ],
        "21": [
          267.811,
          284.901
        ],
        "22": [
          284.901,
          292.702
        ],
        "23": [
          292.702,
          302.682
        ],
        "24": [
          302.682,
          313.313
        ],
        "25": [
          313.313,
          320.523
        ],
        "26": [
          320.523,
          334.303
        ],
        "27": [
          334.303,
          345.614
        ],
        "28": [
          345.614,
          355.244
        ],
        "29": [
          355.244,
          375.175
        ],
        "3": [
          40.762,
          55.182
        ],
        "30": [
          375.175,
          382.595
        ],
        "31": [
          382.595,
          393.166
        ],
        "32": [
          393.166,
          404.966
        ],
        "33": [
          404.966,
          424.657
        ],
        "34": [
          424.657,
          441.098
        ],
        "35": [
          441.098,
          453.058
        ],
        "36": [
          453.058,
          471.389
        ],
        "37": [
          471.389,
          482.239
        ],
        "38": [
          482.239,
          482.239
        ],
        "4": [
          55.182,
          66.353
        ],
        "5": [
          66.353,
          80.433
        ],
        "6": [
          80.433,
          89.864
        ],
        "7": [
          89.864,
          100.194
        ],
        "8": [
          100.194,
          112.775
        ],
        "9": [
          112.775,
          122.745
        ]
      }
    },
    "14": {
      "14": {
        "1": [
          4.63,
          14.19
        ],
        "10": [
          105.072,
          121.272
        ],
        "11": [
          121.272,
          136.083
        ],
        "12": [
          136.083,
          151.763
        ],
        "13": [
          151.763,
          161.253
        ],
        "14": [
          161.253,
          167.733
        ],
        "15": [
          167.733,
          174.234
        ],
        "16": [
          174.234,
          185.084
        ],
        "17": [
          185.084,
          201.264
        ],
        "18": [
          201.264,
          207.524
        ],
        "19": [
          207.524,
          218.124
        ],
        "2": [
          14.19,
          26.841
        ],
        "20": [
          218.124,
          227.775
        ],
        "21": [
          227.775,
          248.305
        ],
        "22": [
          248.305,
          259.465
        ],
        "23": [
          259.465,
          274.886
        ],
        "24": [
          274.886,
          287.916
        ],
        "25": [
          287.916,
          293.876
        ],
        "26": [
          293.876,
          312.586
        ],
        "27": [
          312.586,
          327.357
        ],
        "28": [
          327.357,
          350.607
        ],
        "29": [
          350.607,
          361.327
        ],
        "3": [
          26.841,
          40.181
        ],
        "30": [
          361.327,
          374.398
        ],
        "31": [
          374.398,
          374.398
        ],
        "4": [
          40.181,
          47.831
        ],
        "5": [
          47.831,
          58.611
        ],
        "6": [
          58.611,
          70.391
        ],
        "7": [
          70.391,
          79.652
        ],
        "8": [
          79.652,
          86.902
        ],
        "9": [
          86.902,
          105.072
        ]
      }
    },
    "15": {
      "15": {
        "1": [
          4.6,
          10.15
        ],
        "10": [
          106.653,
          119.133
        ],
        "11": [
          119.133,
          128.113
        ],
        "12": [
          128.113,
          137.783
        ],
        "13": [
          137.783,
          144.053
        ],
        "14": [
          144.053,
          151.324
        ],
        "15": [
          151.324,
          170.684
        ],
        "16": [
          170.684,
          191.345
        ],
        "17": [
          191.345,
          199.355
        ],
        "18": [
          199.355,
          208.745
        ],
        "19": [
          208.745,
          224.675
        ],
        "2": [
          10.15,
          23.691
        ],
        "20": [
          224.675,
          245.656
        ],
        "21": [
          245.656,
          255.556
        ],
        "22": [
          255.556,
          273.336
        ],
        "23": [
          273.336,
          279.967
        ],
        "24": [
          279.967,
          299.727
        ],
        "25": [
          299.727,
          315.867
        ],
        "26": [
          315.867,
          329.518
        ],
        "27": [
          329.518,
          329.518
        ],
        "3": [
          23.691,
          30.821
        ],
        "4": [
          30.821,
          46.441
        ],
        "5": [
          46.441,
          62.701
        ],
        "6": [
          62.701,
          78.642
        ],
        "7": [
          78.642,
          89.712
        ],
        "8": [
          89.712,
          96.862
        ],
        "9": [
          96.862,
          106.653
        ]
      }
    },
    "16": {
      "16": {
        "1": [
          3.63,
          12.15
        ],
        "10": [
          97.904,
          109.094
        ],
        "11": [
          109.094,
          122.055
        ],
        "12": [
          122.055,
          131.195
        ],
        "13": [
          131.195,
          150.836
        ],
        "14": [
          150.836,
          158.336
        ],
        "15": [
          158.336,
          169.277
        ],
        "16": [
          169.277,
          179.547
        ],
        "17": [
          179.547,
          200.028
        ],
        "18": [
          200.028,
          210.238
        ],
        "19": [
          210.238,
          229.039
        ],
        "2": [
          12.15,
          22.291
        ],
        "20": [
          229.039,
          241.68
        ],
        "21": [
          241.68,
          255.01
        ],
        "22": [
          255.01,
          268.581
        ],
        "23": [
          268.581,
          283.241
        ],
        "24": [
          283.241,
          291.752
        ],
        "25": [
          291.752,
          305.312
        ],
        "26": [
          305.312,
          315.973
        ],
        "27": [
          315.973,
          330.063
        ],
        "28": [
          330.063,
          340.074
        ],
        "29": [
          340.074,
          349.614
        ],
        "3": [
          22.291,
          28.881
        ],
        "30": [
          349.614,
          361.594
        ],
        "31": [
          361.594,
          366.075
        ],
        "32": [
          366.075,
          383.465
        ],
        "33": [
          383.465,
          383.465
        ],
        "4": [
          28.881,
          46.142
        ],
        "5": [
          46.142,
          56.712
        ],
        "6": [
          56.712,
          63.343
        ],
        "7": [
          63.343,
          79.773
        ],
        "8": [
          79.773,
          90.094
        ],
        "9": [
          90.094,
          97.904
        ]
      }
    },
    "17": {
      "17": {
        "1": [
          4.12,
          19.871
        ],
        "10": [
          122.817,
          134.767
        ],
        "11": [
          134.767,
          160.119
        ],
        "12": [
          160.119,
          186.33
        ],
        "13": [
          186.33,
          197.931
        ],
        "14": [
          197.931,
          211.492
        ],
        "15": [
          211.492,
          224.032
        ],
        "16": [
          224.032,
          229.302
        ],
        "17": [
          229.302,
          234.683
        ],
        "18": [
          234.683,
          243.453
        ],
        "19": [
          243.453,
          251.694
        ],
        "2": [
          19.871,
          32.692
        ],
        "20": [
          251.694,
          263.914
        ],
        "21": [
          263.914,
          283.855
        ],
        "22": [
          283.855,
          297.096
        ],
        "23": [
          297.096,
          314.777
        ],
        "24": [
          314.777,
          338.898
        ],
        "25": [
          338.898,
          350.659
        ],
        "26": [
          350.659,
          350.659
        ],
        "3": [
          32.692,
          42.652
        ],
        "4": [
          42.652,
          52.213
        ],
        "5": [
          52.213,
          64.954
        ],
        "6": [
          64.954,
          79.944
        ],
        "7": [
          79.944,
          87.815
        ],
        "8": [
          87.815,
          107.516
        ],
        "9": [
          107.516,
          122.817
        ]
      }
    },
    "18": {
      "18": {
        "1": [
          4.57,
          18.781
        ],
        "10": [
          117.684,
          131.454
        ],
        "11": [
          131.454,
          143.254
        ],
        "12": [
          143.254,
          154.245
        ],
        "13": [
          154.245,
          164.045
        ],
        "14": [
          164.045,
          178.776
        ],
        "15": [
          178.776,
          194.216
        ],
        "16": [
          194.216,
          210.457
        ],
        "17": [
          210.457,
          222.047
        ],
        "18": [
          222.047,
          238.527
        ],
        "19": [
          238.527,
          246.718
        ],
        "2": [
          18.781,
          33.671
        ],
        "20": [
          246.718,
          265.268
        ],
        "21": [
          265.268,
          277.659
        ],
        "22": [
          277.659,
          293.549
        ],
        "23": [
          293.549,
          304.119
        ],
        "24": [
          304.119,
          309.03
        ],
        "25": [
          309.03,
          325.46
        ],
        "26": [
          325.46,
          341.071
        ],
        "27": [
          341.071,
          345.891
        ],
        "28": [
          345.891,
          367.961
        ],
        "29": [
          367.961,
          377.472
        ],
        "3": [
          33.671,
          49.872
        ],
        "30": [
          377.472,
          386.822
        ],
        "31": [
          386.822,
          400.642
        ],
        "32": [
          400.642,
          410.263
        ],
        "33": [
          410.263,
          422.723
        ],
        "34": [
          422.723,
          429.943
        ],
        "35": [
          429.943,
          441.324
        ],
        "36": [
          441.324,
          458.974
        ],
        "37": [
          458.974,
          478.555
        ],
        "38": [
          478.555,
          492.485
        ],
        "39": [
          492.485,
          503.856
        ],
        "4": [
          49.872,
          62.192
        ],
        "40": [
          503.856,
          503.856
        ],
        "5": [
          62.192,
          77.782
        ],
        "6": [
          77.782,
          86.173
        ],
        "7": [
          86.173,
          95.043
        ],
        "8": [
          95.043,
          105.353
        ],
        "9": [
          105.353,
          117.684
        ]
      }
    },
    "19": {
      "19": {
        "1": [
          3.9,
          11.21
        ],
        "10": [
          97.554,
          112.145
        ],
        "11": [
          112.145,
          126.015
        ],
        "12": [
          126.015,
          145.206
        ],
        "13": [
          145.206,
          163.007
        ],
        "14": [
          163.007,
          173.607
        ],
        "15": [
          173.607,
          191.628
        ],
        "16": [
          191.628,
          199.829
        ],
        "17": [
          199.829,
          211.949
        ],
        "18": [
          211.949,
          222.91
        ],
        "19": [
          222.91,
          234.3
        ],
        "2": [
          11.21,
          19.651
        ],
        "20": [
          234.3,
          249.201
        ],
        "21": [
          249.201,
          261.641
        ],
        "22": [
          261.641,
          266.382
        ],
        "23": [
          266.382,
          287.072
        ],
        "24": [
          287.072,
          313.594
        ],
        "25": [
          313.594,
          325.644
        ],
        "26": [
          325.644,
          346.285
        ],
        "27": [
          346.285,
          354.845
        ],
        "28": [
          354.845,
          367.236
        ],
        "29": [
          367.236,
          379.996
        ],
        "3": [
          19.651,
          26.351
        ],
        "30": [
          379.996,
          391.107
        ],
        "31": [
          391.107,
          416.758
        ],
        "32": [
          416.758,
          424.358
        ],
        "33": [
          424.358,
          433.859
        ],
        "34": [
          433.859,
          442.309
        ],
        "35": [
          442.309,
          458.28
        ],
        "36": [
          458.28,
          469.36
        ],
        "37": [
          469.36,
          478.921
        ],
        "38": [
          478.921,
          501.322
        ],
        "39": [
          501.322,
          515.582
        ],
        "4": [
          26.351,
          40.792
        ],
        "40": [
          515.582,
          530.263
        ],
        "41": [
          530.263,
          543.143
        ],
        "42": [
          543.143,
          543.143
        ],
        "5": [
          40.792,
          49.902
        ],
        "6": [
          49.902,
          69.753
        ],
        "7": [
          69.753,
          81.464
        ],
        "8": [
          81.464,
          87.044
        ],
        "9": [
          87.044,
          97.554
        ]
      }
    },
    "2": {
      "2": {
        "1": [
          4.42,
          11.971
        ],
        "10": [
          85.527,
          101.818
        ],
        "11": [
          101.818,
          114.739
        ],
        "12": [
          114.739,
          127.18
        ],
        "13": [
          127.18,
          134.0
        ],
        "14": [
          134.0,
          147.871
        ],
        "15": [
          147.871,
          161.352
        ],
        "16": [
          161.352,
          170.383
        ],
        "17": [
          170.383,
          179.584
        ],
        "18": [
          179.584,
          194.215
        ],
        "19": [
          194.215,
          201.785
        ],
        "2": [
          11.971,
          16.601
        ],
        "20": [
          201.785,
          211.216
        ],
        "21": [
          211.216,
          214.466
        ],
        "22": [
          214.466,
          232.408
        ],
        "23": [
          232.408,
          244.419
        ],
        "24": [
          244.419,
          250.239
        ],
        "25": [
          250.239,
          250.239
        ],
        "3": [
          16.601,
          25.662
        ],
        "4": [
          25.662,
          34.313
        ],
        "5": [
          34.313,
          40.853
        ],
        "6": [
          40.853,
          56.144
        ],
        "7": [
          56.144,
          63.985
        ],
        "8": [
          63.985,
          71.755
        ],
        "9": [
          71.755,
          85.527
        ]
      }
    },
    "20": {
      "20": {
        "1": [
          3.84,
          19.291
        ],
        "10": [
          99.515,
          104.285
        ],
        "11": [
          104.285,
          113.986
        ],
        "12": [
          113.986,
          126.966
        ],
        "13": [
          126.966,
          141.067
        ],
        "14": [
          141.067,
          153.148
        ],
        "15": [
          153.148,
          172.779
        ],
        "16": [
          172.779,
          181.699
        ],
        "17": [
          181.699,
          206.76
        ],
        "18": [
          206.76,
          218.221
        ],
        "19": [
          218.221,
          236.072
        ],
        "2": [
          19.291,
          35.662
        ],
        "20": [
          236.072,
          248.423
        ],
        "21": [
          248.423,
          259.753
        ],
        "22": [
          259.753,
          269.634
        ],
        "23": [
          269.634,
          283.744
        ],
        "24": [
          283.744,
          295.135
        ],
        "25": [
          295.135,
          320.166
        ],
        "26": [
          320.166,
          336.957
        ],
        "27": [
          336.957,
          351.008
        ],
        "28": [
          351.008,
          356.508
        ],
        "29": [
          356.508,
          368.739
        ],
        "3": [
          35.662,
          41.242
        ],
        "30": [
          368.739,
          378.529
        ],
        "31": [
          378.529,
          378.529
        ],
        "4": [
          41.242,
          50.303
        ],
        "5": [
          50.303,
          59.793
        ],
        "6": [
          59.793,
          69.894
        ],
        "7": [
          69.894,
          80.734
        ],
        "8": [
          80.734,
          90.395
        ],
        "9": [
          90.395,
          99.515
        ]
      }
    },
    "21": {
      "21": {
        "1": [
          3.69,
          14.051
        ],
        "10": [
          115.935,
          122.585
        ],
        "11": [
          122.585,
          135.096
        ],
        "12": [
          135.096,
          151.097
        ],
        "13": [
          151.097,
          157.427
        ],
        "14": [
          157.427,
          166.327
        ],
        "15": [
          166.327,
          189.328
        ],
        "16": [
          189.328,
          207.309
        ],
        "17": [
          207.309,
          234.8
        ],
        "18": [
          234.8,
          259.121
        ],
        "19": [
          259.121,
          273.472
        ],
        "2": [
          14.051,
          26.811
        ],
        "20": [
          273.472,
          295.713
        ],
        "21": [
          295.713,
          304.463
        ],
        "22": [
          304.463,
          317.054
        ],
        "23": [
          317.054,
          336.375
        ],
        "24": [
          336.375,
          345.515
        ],
        "25": [
          345.515,
          345.515
        ],
        "3": [
          26.811,
          43.182
        ],
        "4": [
          43.182,
          52.722
        ],
        "5": [
          52.722,
          60.143
        ],
        "6": [
          60.143,
          74.023
        ],
        "7": [
          74.023,
          96.054
        ],
        "8": [
          96.054,
          108.485
        ],
        "9": [
          108.485,
          115.935
        ]
      }
    },
    "3": {
      "3": {
        "1": [
          4.02,
          16.461
        ],
        "10": [
          126.806,
          134.766
        ],
        "11": [
          134.766,
          150.797
        ],
        "12": [
          150.797,
          162.257
        ],
        "13": [
          162.257,
          175.618
        ],
        "14": [
          175.618,
          181.748
        ],
        "15": [
          181.748,
          194.049
        ],
        "16": [
          194.049,
          211.459
        ],
        "17": [
          211.459,
          225.59
        ],
        "18": [
          225.59,
          243.011
        ],
        "19": [
          243.011,
          258.761
        ],
        "2": [
          16.461,
          42.962
        ],
        "20": [
          258.761,
          272.652
        ],
        "21": [
          272.652,
          283.693
        ],
        "22": [
          283.693,
          295.333
        ],
        "23": [
          295.333,
          311.854
        ],
        "24": [
          311.854,
          316.714
        ],
        "25": [
          316.714,
          325.334
        ],
        "26": [
          325.334,
          342.595
        ],
        "27": [
          342.595,
          350.916
        ],
        "28": [
          350.916,
          361.626
        ],
        "29": [
          361.626,
          382.127
        ],
        "3": [
          42.962,
          58.523
        ],
        "30": [
          382.127,
          387.027
        ],
        "31": [
          387.027,
          400.918
        ],
        "32": [
          400.918,
          410.538
        ],
        "33": [
          410.538,
          417.319
        ],
        "34": [
          417.319,
          426.269
        ],
        "35": [
          426.269,
          433.169
        ],
        "36": [
          433.169,
          433.169
        ],
        "4": [
          58.523,
          73.143
        ],
        "5": [
          73.143,
          89.084
        ],
        "6": [
          89.084,
          97.474
        ],
        "7": [
          97.474,
          104.105
        ],
        "8": [
          104.105,
          120.385
        ],
        "9": [
          120.385,
          126.806
        ]
      }
    },
    "4": {
      "4": {
        "1": [
          3.19,
          16.531
        ],
        "10": [
          87.743,
          102.703
        ],
        "11": [
          102.703,
          114.324
        ],
        "12": [
          114.324,
          126.434
        ],
        "13": [
          126.434,
          134.404
        ],
        "14": [
          134.404,
          151.025
        ],
        "15": [
          151.025,
          164.025
        ],
        "16": [
          164.025,
          169.925
        ],
        "17": [
          169.925,
          179.276
        ],
        "18": [
          179.276,
          189.976
        ],
        "19": [
          189.976,
          196.596
        ],
        "2": [
          16.531,
          23.541
        ],
        "20": [
          196.596,
          208.217
        ],
        "21": [
          208.217,
          224.207
        ],
        "22": [
          224.207,
          235.498
        ],
        "23": [
          235.498,
          250.338
        ],
        "24": [
          250.338,
          259.218
        ],
        "25": [
          259.218,
          273.069
        ],
        "26": [
          273.069,
          280.989
        ],
        "27": [
          280.989,
          301.74
        ],
        "28": [
          301.74,
          308.64
        ],
        "29": [
          308.64,
          318.13
        ],
        "3": [
          23.541,
          27.981
        ],
        "30": [
          318.13,
          324.29
        ],
        "31": [
          324.29,
          331.481
        ],
        "32": [
          331.481,
          338.581
        ],
        "33": [
          338.581,
          348.701
        ],
        "34": [
          348.701,
          361.312
        ],
        "35": [
          361.312,
          379.152
        ],
        "36": [
          379.152,
          396.933
        ],
        "37": [
          396.933,
          406.263
        ],
        "38": [
          406.263,
          415.123
        ],
        "39": [
          415.123,
          428.734
        ],
        "4": [
          27.981,
          32.591
        ],
        "40": [
          428.734,
          442.004
        ],
        "41": [
          442.004,
          448.374
        ],
        "42": [
          448.374,
          464.985
        ],
        "43": [
          464.985,
          473.445
        ],
        "44": [
          473.445,
          480.445
        ],
        "45": [
          480.445,
          500.376
        ],
        "46": [
          500.376,
          517.717
        ],
        "47": [
          517.717,
          538.067
        ],
        "48": [
          538.067,
          550.858
        ],
        "49": [
          550.858,
          559.228
        ],
        "5": [
          32.591,
          45.001
        ],
        "50": [
          559.228,
          570.218
        ],
        "51": [
          570.218,
          582.869
        ],
        "52": [
          582.869,
          594.229
        ],
        "53": [
          594.229,
          614.79
        ],
        "54": [
          614.79,
          614.79
        ],
        "6": [
          45.001,
          55.602
        ],
        "7": [
          55.602,
          60.202
        ],
        "8": [
          60.202,
          69.062
        ],
        "9": [
          69.062,
          87.743
        ]
      }
    },
    "5": {
      "5": {
        "1": [
          2.78,
          10.95
        ],
        "10": [
          115.002,
          128.992
        ],
        "11": [
          128.992,
          136.572
        ],
        "12": [
          136.572,
          145.432
        ],
        "13": [
          145.432,
          156.122
        ],
        "14": [
          156.122,
          171.772
        ],
        "15": [
          171.772,
          182.303
        ],
        "16": [
          182.303,
          196.643
        ],
        "17": [
          196.643,
          205.793
        ],
        "18": [
          205.793,
          223.813
        ],
        "19": [
          223.813,
          241.253
        ],
        "2": [
          10.95,
          26.15
        ],
        "20": [
          241.253,
          259.184
        ],
        "21": [
          259.184,
          271.114
        ],
        "22": [
          271.114,
          293.284
        ],
        "23": [
          293.284,
          316.354
        ],
        "24": [
          316.354,
          333.335
        ],
        "25": [
          333.335,
          346.285
        ],
        "26": [
          346.285,
          354.225
        ],
        "27": [
          354.225,
          366.295
        ],
        "28": [
          366.295,
          381.045
        ],
        "29": [
          381.045,
          396.886
        ],
        "3": [
          26.15,
          41.641
        ],
        "30": [
          396.886,
          403.566
        ],
        "31": [
          403.566,
          415.776
        ],
        "32": [
          415.776,
          421.926
        ],
        "33": [
          421.926,
          427.966
        ],
        "34": [
          427.966,
          437.726
        ],
        "35": [
          437.726,
          456.486
        ],
        "36": [
          456.486,
          468.997
        ],
        "37": [
          468.997,
          479.027
        ],
        "38": [
          479.027,
          493.527
        ],
        "39": [
          493.527,
          500.067
        ],
        "4": [
          41.641,
          60.501
        ],
        "40": [
          500.067,
          503.737
        ],
        "41": [
          503.737,
          509.837
        ],
        "42": [
          509.837,
          524.027
        ],
        "43": [
          524.027,
          536.887
        ],
        "44": [
          536.887,
          551.348
        ],
        "45": [
          551.348,
          561.908
        ],
        "46": [
          561.908,
          561.908
        ],
        "47": [
          561.908,
          561.908
        ],
        "5": [
          60.501,
          64.661
        ],
        "6": [
          64.661,
          81.041
        ],
        "7": [
          81.041,
          98.751
        ],
        "8": [
          98.751,
          105.491
        ],
        "9": [
          105.491,
          115.002
        ]
      }
    },
    "6": {
      "6": {
        "1": [
          3.11,
          11.97
        ],
        "10": [
          84.261,
          95.381
        ],
        "11": [
          95.381,
          113.051
        ],
        "12": [
          113.051,
          123.881
        ],
        "13": [
          123.881,
          135.461
        ],
        "14": [
          135.461,
          145.961
        ],
        "15": [
          145.961,
          161.752
        ],
        "16": [
          161.752,
          169.422
        ],
        "17": [
          169.422,
          182.202
        ],
        "18": [
          182.202,
          188.062
        ],
        "19": [
          188.062,
          200.642
        ],
        "2": [
          11.97,
          23.5
        ],
        "20": [
          200.642,
          205.352
        ],
        "21": [
          205.352,
          215.822
        ],
        "22": [
          215.822,
          238.282
        ],
        "23": [
          238.282,
          249.063
        ],
        "24": [
          249.063,
          261.523
        ],
        "25": [
          261.523,
          271.803
        ],
        "26": [
          271.803,
          286.933
        ],
        "27": [
          286.933,
          304.523
        ],
        "28": [
          304.523,
          311.843
        ],
        "29": [
          311.843,
          321.373
        ],
        "3": [
          23.5,
          29.9
        ],
        "30": [
          321.373,
          333.293
        ],
        "31": [
          333.293,
          347.723
        ],
        "32": [
          347.723,
          363.454
        ],
        "33": [
          363.454,
          373.754
        ],
        "34": [
          373.754,
          380.764
        ],
        "35": [
          380.764,
          395.994
        ],
        "36": [
          395.994,
          402.564
        ],
        "37": [
          402.564,
          413.704
        ],
        "38": [
          413.704,
          424.334
        ],
        "39": [
          424.334,
          440.844
        ],
        "4": [
          29.9,
          34.36
        ],
        "40": [
          440.844,
          456.485
        ],
        "41": [
          456.485,
          466.645
        ],
        "42": [
          466.645,
          480.975
        ],
        "43": [
          480.975,
          485.395
        ],
        "44": [
          485.395,
          497.355
        ],
        "45": [
          497.355,
          510.645
        ],
        "46": [
          510.645,
          518.975
        ],
        "47": [
          518.975,
          528.715
        ],
        "48": [
          528.715,
          532.275
        ],
        "49": [
          532.275,
          538.995
        ],
        "5": [
          34.36,
          46.15
        ],
        "50": [
          538.995,
          547.095
        ],
        "51": [
          547.095,
          563.976
        ],
        "52": [
          563.976,
          572.356
        ],
        "53": [
          572.356,
          589.576
        ],
        "54": [
          589.576,
          600.956
        ],
        "55": [
          600.956,
          610.846
        ],
        "56": [
          610.846,
          620.096
        ],
        "57": [
          620.096,
          632.896
        ],
        "58": [
          632.896,
          648.457
        ],
        "59": [
          648.457,
          657.077
        ],
        "6": [
          46.15,
          56.871
        ],
        "60": [
          657.077,
          667.977
        ],
        "61": [
          667.977,
          684.337
        ],
        "62": [
          684.337,
          695.097
        ],
        "63": [
          695.097,
          707.997
        ],
        "64": [
          707.997,
          721.587
        ],
        "65": [
          721.587,
          734.427
        ],
        "66": [
          734.427,
          742.237
        ],
        "67": [
          742.237,
          749.388
        ],
        "68": [
          749.388,
          762.698
        ],
        "69": [
          762.698,
          772.418
        ],
        "7": [
          56.871,
          68.141
        ],
        "70": [
          772.418,
          781.098
        ],
        "71": [
          781.098,
          781.098
        ],
        "8": [
          68.141,
          74.141
        ],
        "9": [
          74.141,
          84.261
        ]
      }
    },
    "7": {
      "7": {
        "1": [
          3.71,
          21.941
        ],
        "10": [
          91.374,
          100.745
        ],
        "11": [
          100.745,
          109.055
        ],
        "12": [
          109.055,
          120.255
        ],
        "13": [
          120.255,
          128.416
        ],
        "14": [
          128.416,
          135.626
        ],
        "15": [
          135.626,
          144.156
        ],
        "16": [
          144.156,
          152.187
        ],
        "17": [
          152.187,
          163.747
        ],
        "18": [
          163.747,
          177.128
        ],
        "19": [
          177.128,
          186.828
        ],
        "2": [
          21.941,
          26.131
        ],
        "20": [
          186.828,
          192.289
        ],
        "21": [
          192.289,
          200.199
        ],
        "22": [
          200.199,
          214.94
        ],
        "23": [
          214.94,
          231.46
        ],
        "24": [
          231.46,
          237.961
        ],
        "25": [
          237.961,
          248.471
        ],
        "26": [
          248.471,
          261.012
        ],
        "27": [
          261.012,
          271.362
        ],
        "28": [
          271.362,
          289.323
        ],
        "29": [
          289.323,
          296.103
        ],
        "3": [
          26.131,
          38.122
        ],
        "30": [
          296.103,
          307.304
        ],
        "31": [
          307.304,
          318.234
        ],
        "32": [
          318.234,
          332.095
        ],
        "33": [
          332.095,
          342.685
        ],
        "34": [
          342.685,
          350.106
        ],
        "35": [
          350.106,
          366.216
        ],
        "36": [
          366.216,
          379.227
        ],
        "37": [
          379.227,
          395.778
        ],
        "38": [
          395.778,
          407.058
        ],
        "39": [
          407.058,
          428.079
        ],
        "4": [
          38.122,
          51.912
        ],
        "40": [
          428.079,
          436.88
        ],
        "41": [
          436.88,
          447.07
        ],
        "42": [
          447.07,
          457.39
        ],
        "43": [
          457.39,
          461.571
        ],
        "44": [
          461.571,
          468.581
        ],
        "45": [
          468.581,
          478.641
        ],
        "46": [
          478.641,
          486.172
        ],
        "47": [
          486.172,
          490.932
        ],
        "48": [
          490.932,
          497.672
        ],
        "49": [
          497.672,
          503.202
        ],
        "5": [
          51.912,
          57.433
        ],
        "50": [
          503.202,
          511.323
        ],
        "51": [
          511.323,
          521.083
        ],
        "52": [
          521.083,
          531.904
        ],
        "53": [
          531.904,
          531.904
        ],
        "6": [
          57.433,
          67.243
        ],
        "7": [
          67.243,
          79.094
        ],
        "8": [
          79.094,
          86.514
        ],
        "9": [
          86.514,
          91.374
        ]
      }
    },
    "8": {
      "8": {
        "1": [
          3.48,
          7.98
        ],
        "10": [
          103.773,
          118.283
        ],
        "11": [
          118.283,
          133.134
        ],
        "12": [
          133.134,
          151.584
        ],
        "13": [
          151.584,
          160.375
        ],
        "14": [
          160.375,
          180.345
        ],
        "15": [
          180.345,
          186.796
        ],
        "16": [
          186.796,
          200.096
        ],
        "17": [
          200.096,
          206.366
        ],
        "18": [
          206.366,
          216.416
        ],
        "19": [
          216.416,
          232.677
        ],
        "2": [
          7.98,
          20.051
        ],
        "20": [
          232.677,
          248.657
        ],
        "21": [
          248.657,
          261.868
        ],
        "22": [
          261.868,
          271.898
        ],
        "23": [
          271.898,
          282.018
        ],
        "24": [
          282.018,
          294.819
        ],
        "25": [
          294.819,
          305.959
        ],
        "26": [
          305.959,
          320.949
        ],
        "27": [
          320.949,
          328.11
        ],
        "28": [
          328.11,
          346.33
        ],
        "29": [
          346.33,
          358.541
        ],
        "3": [
          20.051,
          33.171
        ],
        "30": [
          358.541,
          365.231
        ],
        "31": [
          365.231,
          378.071
        ],
        "32": [
          378.071,
          383.551
        ],
        "33": [
          383.551,
          396.632
        ],
        "34": [
          396.632,
          404.692
        ],
        "35": [
          404.692,
          409.762
        ],
        "36": [
          409.762,
          417.092
        ],
        "37": [
          417.092,
          427.243
        ],
        "38": [
          427.243,
          437.773
        ],
        "39": [
          437.773,
          449.233
        ],
        "4": [
          33.171,
          40.861
        ],
        "40": [
          449.233,
          458.724
        ],
        "41": [
          458.724,
          469.674
        ],
        "42": [
          469.674,
          488.274
        ],
        "43": [
          488.274,
          494.235
        ],
        "44": [
          494.235,
          519.045
        ],
        "45": [
          519.045,
          525.375
        ],
        "46": [
          525.375,
          536.356
        ],
        "47": [
          536.356,
          546.246
        ],
        "48": [
          546.246,
          555.186
        ],
        "49": [
          555.186,
          563.857
        ],
        "5": [
          40.861,
          50.411
        ],
        "50": [
          563.857,
          570.847
        ],
        "51": [
          570.847,
          579.397
        ],
        "52": [
          579.397,
          598.248
        ],
        "53": [
          598.248,
          607.948
        ],
        "54": [
          607.948,
          624.278
        ],
        "55": [
          624.278,
          639.239
        ],
        "56": [
          639.239,
          649.859
        ],
        "57": [
          649.859,
          658.739
        ],
        "58": [
          658.739,
          667.32
        ],
        "59": [
          667.32,
          667.32
        ],
        "6": [
          50.411,
          64.872
        ],
        "7": [
          64.872,
          78.232
        ],
        "8": [
          78.232,
          82.702
        ],
        "9": [
          82.702,
          103.773
        ]
      }
    },
    "9": {
      "9": {
        "1": [
          3.41,
          12.061
        ],
        "10": [
          106.865,
          111.345
        ],
        "11": [
          111.345,
          129.876
        ],
        "12": [
          129.876,
          136.056
        ],
        "13": [
          136.056,
          142.256
        ],
        "14": [
          142.256,
          151.847
        ],
        "15": [
          151.847,
          165.537
        ],
        "16": [
          165.537,
          184.738
        ],
        "17": [
          184.738,
          193.239
        ],
        "18": [
          193.239,
          203.609
        ],
        "19": [
          203.609,
          214.27
        ],
        "2": [
          12.061,
          24.841
        ],
        "20": [
          214.27,
          222.96
        ],
        "21": [
          222.96,
          237.331
        ],
        "22": [
          237.331,
          253.011
        ],
        "23": [
          253.011,
          260.302
        ],
        "24": [
          260.302,
          277.112
        ],
        "25": [
          277.112,
          289.973
        ],
        "26": [
          289.973,
          297.103
        ],
        "27": [
          297.103,
          308.204
        ],
        "28": [
          308.204,
          316.234
        ],
        "29": [
          316.234,
          326.685
        ],
        "3": [
          24.841,
          38.722
        ],
        "30": [
          326.685,
          336.445
        ],
        "31": [
          336.445,
          348.596
        ],
        "32": [
          348.596,
          358.116
        ],
        "33": [
          358.116,
          364.686
        ],
        "34": [
          364.686,
          377.617
        ],
        "35": [
          377.617,
          388.567
        ],
        "36": [
          388.567,
          395.588
        ],
        "37": [
          395.588,
          404.638
        ],
        "38": [
          404.638,
          411.638
        ],
        "39": [
          411.638,
          425.389
        ],
        "4": [
          38.722,
          49.772
        ],
        "40": [
          425.389,
          434.899
        ],
        "41": [
          434.899,
          434.899
        ],
        "5": [
          49.772,
          57.473
        ],
        "6": [
          57.473,
          66.183
        ],
        "7": [
          66.183,
          85.774
        ],
        "8": [
          85.774,
          97.984
        ],
        "9": [
          97.984,
          106.865
        ]
      }
    }
  },
  "warnings": {
    "KFXBIVN1DA": {
      "5": {
        "5": {
          "46-47": {
            "details": "verse 47 missing, timestamps repeated",
            "missing_verses": [
              47
            ],
            "type": "partial"
          }
        }
      }
    }
  }
}