{
  "MAASJVN2DA": {
    "1": {
      "1": {
        "1": [
          7.35,
          16.41
        ],
        "14": [
          99.71,
          110.27
        ],
        "2": [
          16.41,
          19.85
        ],
        "3": [
          19.85,
          28.6
        ],
        "4": [
          28.6,
          37.92
        ],
        "5": [
          37.92,
          46.24
        ]
      }
    }
  },
  "MAASJVN2SA": {
    "1": {
      "1": {
        "1": [
          7.35,
          16.41
        ],
        "14": [
          99.71,
          110.27
        ],
        "2": [
          16.41,
          19.85
        ],
        "3": [
          19.85,
          28.6
        ],
        "4": [
          28.6,
          37.92
        ],
        "5": [
          37.92,
          46.24
        ]
      }
    }
  }
}