{
  "AVAIBTN1DA": {
    "6": {
      "2": {
        "1": [
          4.5,
          10.88
        ],
        "2": [
          10.88,
          19.511
        ],
        "3": [
          19.511,
          29.821
        ],
        "4": [
          29.821,
          37.741
        ]
      },
      "9": {
        "3": [
          34.621,
          41.941
        ],
        "4": [
          41.941,
          51.491
        ],
        "5": [
          51.491,
          61.072
        ],
        "6": [
          61.072,
          67.482
        ]
      }
    }
  }
}