{
  "PSSBIVN1DA": {
    "7": {
      "21": {
        "1": [
          3.44,
          16.24
        ],
        "2": [
          16.24,
          31.921
        ],
        "3": [
          31.921,
          57.241
        ],
        "4": [
          57.241,
          75.212
        ]
      },
      "22": {
        "1": [
          3.08,
          21.091
        ],
        "2": [
          21.091,
          47.392
        ],
        "3": [
          47.392,
          62.803
        ],
        "4": [
          62.803,
          69.213
        ],
        "5": [
          69.213,
          89.524
        ]
      }
    }
  }
}